Workbook

Sheet README
A1: Kenya Industry Opportunity Radar: model
A2: Real data: KNBS Quarterly GDP Q1 2026, CBK Bank Supervision Annual Report 2025, CBK Credit Officer Survey (June 2026), KNBS Economic Survey 2026.
A4: How to read: Scorecard ranks ten industry groups on five pillars. Change the scenario or weights on Inputs; everything recalculates.
A5: Blue cells are inputs; black cells are formulas. GDP and Credit_Map hold the editable mapping of activities and bank sectors to industry groups.
A6: Pillars: Scale (2025 real value added), Recent growth (Q1 2026 vs Q1 2025), Track record (2021-25 CAGR), Credit demand (net % of credit officers seeing higher demand, June 2026, loan-weighted), Credit health (inverse of NPL ratio, Dec 2025).
A7: Each pillar is min-max scaled to 0-100 across the ten groups. Groups with no matching bank sector (Public Sector & Development, Health) get a neutral 50 on the two credit pillars.
A8: Transport and Communication is one CBK bank sector; it is shared by Technology, Media & Telecom and Transport & Logistics.
A9: Industry groups are an analyst grouping for this exercise, not any firm's official taxonomy. Professional services, other services, FISIM and taxes on products are excluded.
A10: Checks sheet compares every headline number with the independent Python calculation (analysis/model.py).

Sheet Scorecard
A1: Industry Opportunity Radar: scorecard
A2: Real KNBS and CBK data. Scenario selected on Inputs. Ranks 1 = highest priority.
A3: Scenario: | B3: =Inputs!B3 -> Balanced
A5: Industry group | B5: Value added 2025 (KSh m) | C5: Share of GDP % | D5: Growth 2025 % | E5: CAGR 2021-25 % | F5: Growth Q1 2026 % | G5: Gross loans (KSh m) | H5: NPL ratio % | I5: Credit demand net % | J5: Scale (0-100) | K5: Recent growth | L5: Track record | M5: Credit demand | N5: Credit health | O5: Score | P5: Rank | Q5: Tier | R5: Evidence
A6: Financial Services | B6: =SUMIFS(GDP!$E$5:$E$21,GDP!$B$5:$B$21,$A6) -> 1134626 | C6: =B6/GDP!$E$22*100 -> 10.836496 | D6: =B6/SUMIFS(GDP!$D$5:$D$21,GDP!$B$5:$B$21,$A6)*100-100 -> 6.5213493 | E6: =((B6/SUMIFS(GDP!$C$5:$C$21,GDP!$B$5:$B$21,$A6))^(1/4)-1)*100 -> 9.0282808 | F6: =SUMIFS(GDP!$G$5:$G$21,GDP!$B$5:$B$21,$A6)/SUMIFS(GDP!$F$5:$F$21,GDP!$B$5:$B$21,$A6)*100-100 -> 6.2783503 | G6: =IF(SUMIFS(Credit_Map!$C$5:$C$15,Credit_Map!$A$5:$A$15,$A6)=0,"",SUMIFS(Credit_Map!$C$5:$C$15,Credit_Map!$A$5:$A$15,$A6)) -> 241698.4 | H6: =IF(G6="","",SUMIFS(Credit_Map!$D$5:$D$15,Credit_Map!$A$5:$A$15,$A6)/G6*100) -> 3.2537245 | I6: =IF(G6="","",SUMPRODUCT((Credit_Map!$A$5:$A$15=$A6)*Credit_Map!$C$5:$C$15*(Credit_Map!$E$5:$E$15-Credit_Map!$F$5:$F$15))/G6) -> 22 | J6: =IF(B6="","",((B6-MIN($B$6:$B$15))/(MAX($B$6:$B$15)-MIN($B$6:$B$15))*100)) -> 52.73637 | K6: =IF(F6="","",((F6-MIN($F$6:$F$15))/(MAX($F$6:$F$15)-MIN($F$6:$F$15))*100)) -> 100 | L6: =IF(E6="","",((E6-MIN($E$6:$E$15))/(MAX($E$6:$E$15)-MIN($E$6:$E$15))*100)) -> 100 | M6: =IF(I6="","",((I6-MIN($I$6:$I$15))/(MAX($I$6:$I$15)-MIN($I$6:$I$15))*100)) -> 30.998016 | N6: =IF(H6="","",100-((H6-MIN($H$6:$H$15))/(MAX($H$6:$H$15)-MIN($H$6:$H$15))*100)) -> 100 | O6: =(IF(ISNUMBER(J6),J6,Inputs!$B$4)*INDEX(Inputs!$B$9:$F$13,MATCH(Inputs!$B$3,Inputs!$A$9:$A$13,0),1)+IF(ISNUMBER(K6),K6,Inputs!$B$4)*INDEX(Inputs!$B$9:$F$13,MATCH(Inputs!$B$3,Inputs!$A$9:$A$13,0),2)+IF(ISNUMBER(L6),L6,Inputs!$B$4)*INDEX(Inputs!$B$9:$F$13,MATCH(Inputs!$B$3,Inputs!$A$9:$A$13,0),3)+IF(ISNUMBER(M6),M6,Inputs!$B$4)*INDEX(Inputs!$B$9:$F$13,MATCH(Inputs!$B$3,Inputs!$A$9:$A$13,0),4)+IF(ISNUMBER(N6),N6,Inputs!$B$4)*INDEX(Inputs!$B$9:$F$13,MATCH(Inputs!$B$3,Inputs!$A$9:$A$13,0),5))/INDEX(Inputs!$G$9:$G$13,MATCH(Inputs!$B$3,Inputs!$A$9:$A$13,0)) -> 76.746877 | P6: =RANK(O6,$O$6:$O$15) -> 1 | Q6: =IF(P6<=Inputs!$B$5,"Lead",IF(P6<=Inputs!$B$6,"Grow","Selective")) -> Lead | R6: =IF(G6="","Growth only (credit neutral)","Growth + credit") -> Growth + credit
A7: Energy & Resources | B7: =SUMIFS(GDP!$E$5:$E$21,GDP!$B$5:$B$21,$A7) -> 385040 | C7: =B7/GDP!$E$22*100 -> 3.6774095 | D7: =B7/SUMIFS(GDP!$D$5:$D$21,GDP!$B$5:$B$21,$A7)*100-100 -> 7.8694495 | E7: =((B7/SUMIFS(GDP!$C$5:$C$21,GDP!$B$5:$B$21,$A7))^(1/4)-1)*100 -> 3.4953054 | F7: =SUMIFS(GDP!$G$5:$G$21,GDP!$B$5:$B$21,$A7)/SUMIFS(GDP!$F$5:$F$21,GDP!$B$5:$B$21,$A7)*100-100 -> 5.6731222 | G7: =IF(SUMIFS(Credit_Map!$C$5:$C$15,Credit_Map!$A$5:$A$15,$A7)=0,"",SUMIFS(Credit_Map!$C$5:$C$15,Credit_Map!$A$5:$A$15,$A7)) -> 180935.1 | H7: =IF(G7="","",SUMIFS(Credit_Map!$D$5:$D$15,Credit_Map!$A$5:$A$15,$A7)/G7*100) -> 9.555581 | I7: =IF(G7="","",SUMPRODUCT((Credit_Map!$A$5:$A$15=$A7)*Credit_Map!$C$5:$C$15*(Credit_Map!$E$5:$E$15-Credit_Map!$F$5:$F$15))/G7) -> 25.99623 | J7: =IF(B7="","",((B7-MIN($B$6:$B$15))/(MAX($B$6:$B$15)-MIN($B$6:$B$15))*100)) -> 7.6458596 | K7: =IF(F7="","",((F7-MIN($F$6:$F$15))/(MAX($F$6:$F$15)-MIN($F$6:$F$15))*100)) -> 77.417487 | L7: =IF(E7="","",((E7-MIN($E$6:$E$15))/(MAX($E$6:$E$15)-MIN($E$6:$E$15))*100)) -> 16.288237 | M7: =IF(I7="","",((I7-MIN($I$6:$I$15))/(MAX($I$6:$I$15)-MIN($I$6:$I$15))*100)) -> 39.846245 | N7: =IF(H7="","",100-((H7-MIN($H$6:$H$15))/(MAX($H$6:$H$15)-MIN($H$6:$H$15))*100)) -> 69.788031 | O7: =(IF(ISNUMBER(J7),J7,Inputs!$B$4)*INDEX(Inputs!$B$9:$F$13,MATCH(Inputs!$B$3,Inputs!$A$9:$A$13,0),1)+IF(ISNUMBER(K7),K7,Inputs!$B$4)*INDEX(Inputs!$B$9:$F$13,MATCH(Inputs!$B$3,Inputs!$A$9:$A$13,0),2)+IF(ISNUMBER(L7),L7,Inputs!$B$4)*INDEX(Inputs!$B$9:$F$13,MATCH(Inputs!$B$3,Inputs!$A$9:$A$13,0),3)+IF(ISNUMBER(M7),M7,Inputs!$B$4)*INDEX(Inputs!$B$9:$F$13,MATCH(Inputs!$B$3,Inputs!$A$9:$A$13,0),4)+IF(ISNUMBER(N7),N7,Inputs!$B$4)*INDEX(Inputs!$B$9:$F$13,MATCH(Inputs!$B$3,Inputs!$A$9:$A$13,0),5))/INDEX(Inputs!$G$9:$G$13,MATCH(Inputs!$B$3,Inputs!$A$9:$A$13,0)) -> 45.253634 | P7: =RANK(O7,$O$6:$O$15) -> 4 | Q7: =IF(P7<=Inputs!$B$5,"Lead",IF(P7<=Inputs!$B$6,"Grow","Selective")) -> Grow | R7: =IF(G7="","Growth only (credit neutral)","Growth + credit") -> Growth + credit
A8: Technology, Media & Telecom | B8: =SUMIFS(GDP!$E$5:$E$21,GDP!$B$5:$B$21,$A8) -> 391886 | C8: =B8/GDP!$E$22*100 -> 3.7427937 | D8: =B8/SUMIFS(GDP!$D$5:$D$21,GDP!$B$5:$B$21,$A8)*100-100 -> 4.821591 | E8: =((B8/SUMIFS(GDP!$C$5:$C$21,GDP!$B$5:$B$21,$A8))^(1/4)-1)*100 -> 7.7969831 | F8: =SUMIFS(GDP!$G$5:$G$21,GDP!$B$5:$B$21,$A8)/SUMIFS(GDP!$F$5:$F$21,GDP!$B$5:$B$21,$A8)*100-100 -> 4.9743935 | G8: =IF(SUMIFS(Credit_Map!$C$5:$C$15,Credit_Map!$A$5:$A$15,$A8)=0,"",SUMIFS(Credit_Map!$C$5:$C$15,Credit_Map!$A$5:$A$15,$A8)) -> 321105.5 | H8: =IF(G8="","",SUMIFS(Credit_Map!$D$5:$D$15,Credit_Map!$A$5:$A$15,$A8)/G8*100) -> 16.561815 | I8: =IF(G8="","",SUMPRODUCT((Credit_Map!$A$5:$A$15=$A8)*Credit_Map!$C$5:$C$15*(Credit_Map!$E$5:$E$15-Credit_Map!$F$5:$F$15))/G8) -> 8 | J8: =IF(B8="","",((B8-MIN($B$6:$B$15))/(MAX($B$6:$B$15)-MIN($B$6:$B$15))*100)) -> 8.0576731 | K8: =IF(F8="","",((F8-MIN($F$6:$F$15))/(MAX($F$6:$F$15)-MIN($F$6:$F$15))*100)) -> 51.346241 | L8: =IF(E8="","",((E8-MIN($E$6:$E$15))/(MAX($E$6:$E$15)-MIN($E$6:$E$15))*100)) -> 81.370944 | M8: =IF(I8="","",((I8-MIN($I$6:$I$15))/(MAX($I$6:$I$15)-MIN($I$6:$I$15))*100)) -> 0 | N8: =IF(H8="","",100-((H8-MIN($H$6:$H$15))/(MAX($H$6:$H$15)-MIN($H$6:$H$15))*100)) -> 36.199176 | O8: =(IF(ISNUMBER(J8),J8,Inputs!$B$4)*INDEX(Inputs!$B$9:$F$13,MATCH(Inputs!$B$3,Inputs!$A$9:$A$13,0),1)+IF(ISNUMBER(K8),K8,Inputs!$B$4)*INDEX(Inputs!$B$9:$F$13,MATCH(Inputs!$B$3,Inputs!$A$9:$A$13,0),2)+IF(ISNUMBER(L8),L8,Inputs!$B$4)*INDEX(Inputs!$B$9:$F$13,MATCH(Inputs!$B$3,Inputs!$A$9:$A$13,0),3)+IF(ISNUMBER(M8),M8,Inputs!$B$4)*INDEX(Inputs!$B$9:$F$13,MATCH(Inputs!$B$3,Inputs!$A$9:$A$13,0),4)+IF(ISNUMBER(N8),N8,Inputs!$B$4)*INDEX(Inputs!$B$9:$F$13,MATCH(Inputs!$B$3,Inputs!$A$9:$A$13,0),5))/INDEX(Inputs!$G$9:$G$13,MATCH(Inputs!$B$3,Inputs!$A$9:$A$13,0)) -> 33.893572 | P8: =RANK(O8,$O$6:$O$15) -> 7 | Q8: =IF(P8<=Inputs!$B$5,"Lead",IF(P8<=Inputs!$B$6,"Grow","Selective")) -> Grow | R8: =IF(G8="","Growth only (credit neutral)","Growth + credit") -> Growth + credit
A9: Transport & Logistics | B9: =SUMIFS(GDP!$E$5:$E$21,GDP!$B$5:$B$21,$A9) -> 1077187 | C9: =B9/GDP!$E$22*100 -> 10.287912 | D9: =B9/SUMIFS(GDP!$D$5:$D$21,GDP!$B$5:$B$21,$A9)*100-100 -> 3.6957208 | E9: =((B9/SUMIFS(GDP!$C$5:$C$21,GDP!$B$5:$B$21,$A9))^(1/4)-1)*100 -> 4.8295283 | F9: =SUMIFS(GDP!$G$5:$G$21,GDP!$B$5:$B$21,$A9)/SUMIFS(GDP!$F$5:$F$21,GDP!$B$5:$B$21,$A9)*100-100 -> 3.5982762 | G9: =IF(SUMIFS(Credit_Map!$C$5:$C$15,Credit_Map!$A$5:$A$15,$A9)=0,"",SUMIFS(Credit_Map!$C$5:$C$15,Credit_Map!$A$5:$A$15,$A9)) -> 321105.5 | H9: =IF(G9="","",SUMIFS(Credit_Map!$D$5:$D$15,Credit_Map!$A$5:$A$15,$A9)/G9*100) -> 16.561815 | I9: =IF(G9="","",SUMPRODUCT((Credit_Map!$A$5:$A$15=$A9)*Credit_Map!$C$5:$C$15*(Credit_Map!$E$5:$E$15-Credit_Map!$F$5:$F$15))/G9) -> 8 | J9: =IF(B9="","",((B9-MIN($B$6:$B$15))/(MAX($B$6:$B$15)-MIN($B$6:$B$15))*100)) -> 49.281191 | K9: =IF(F9="","",((F9-MIN($F$6:$F$15))/(MAX($F$6:$F$15)-MIN($F$6:$F$15))*100)) -> 0 | L9: =IF(E9="","",((E9-MIN($E$6:$E$15))/(MAX($E$6:$E$15)-MIN($E$6:$E$15))*100)) -> 36.474509 | M9: =IF(I9="","",((I9-MIN($I$6:$I$15))/(MAX($I$6:$I$15)-MIN($I$6:$I$15))*100)) -> 0 | N9: =IF(H9="","",100-((H9-MIN($H$6:$H$15))/(MAX($H$6:$H$15)-MIN($H$6:$H$15))*100)) -> 36.199176 | O9: =(IF(ISNUMBER(J9),J9,Inputs!$B$4)*INDEX(Inputs!$B$9:$F$13,MATCH(Inputs!$B$3,Inputs!$A$9:$A$13,0),1)+IF(ISNUMBER(K9),K9,Inputs!$B$4)*INDEX(Inputs!$B$9:$F$13,MATCH(Inputs!$B$3,Inputs!$A$9:$A$13,0),2)+IF(ISNUMBER(L9),L9,Inputs!$B$4)*INDEX(Inputs!$B$9:$F$13,MATCH(Inputs!$B$3,Inputs!$A$9:$A$13,0),3)+IF(ISNUMBER(M9),M9,Inputs!$B$4)*INDEX(Inputs!$B$9:$F$13,MATCH(Inputs!$B$3,Inputs!$A$9:$A$13,0),4)+IF(ISNUMBER(N9),N9,Inputs!$B$4)*INDEX(Inputs!$B$9:$F$13,MATCH(Inputs!$B$3,Inputs!$A$9:$A$13,0),5))/INDEX(Inputs!$G$9:$G$13,MATCH(Inputs!$B$3,Inputs!$A$9:$A$13,0)) -> 22.56725 | P9: =RANK(O9,$O$6:$O$15) -> 10 | Q9: =IF(P9<=Inputs!$B$5,"Lead",IF(P9<=Inputs!$B$6,"Grow","Selective")) -> Selective | R9: =IF(G9="","Growth only (credit neutral)","Growth + credit") -> Growth + credit
A10: Public Sector & Development | B10: =SUMIFS(GDP!$E$5:$E$21,GDP!$B$5:$B$21,$A10) -> 1273606 | C10: =B10/GDP!$E$22*100 -> 12.163855 | D10: =B10/SUMIFS(GDP!$D$5:$D$21,GDP!$B$5:$B$21,$A10)*100-100 -> 5.9295658 | E10: =((B10/SUMIFS(GDP!$C$5:$C$21,GDP!$B$5:$B$21,$A10))^(1/4)-1)*100 -> 5.5228987 | F10: =SUMIFS(GDP!$G$5:$G$21,GDP!$B$5:$B$21,$A10)/SUMIFS(GDP!$F$5:$F$21,GDP!$B$5:$B$21,$A10)*100-100 -> 5.9081245 | G10: =IF(SUMIFS(Credit_Map!$C$5:$C$15,Credit_Map!$A$5:$A$15,$A10)=0,"",SUMIFS(Credit_Map!$C$5:$C$15,Credit_Map!$A$5:$A$15,$A10)) | H10: =IF(G10="","",SUMIFS(Credit_Map!$D$5:$D$15,Credit_Map!$A$5:$A$15,$A10)/G10*100) | I10: =IF(G10="","",SUMPRODUCT((Credit_Map!$A$5:$A$15=$A10)*Credit_Map!$C$5:$C$15*(Credit_Map!$E$5:$E$15-Credit_Map!$F$5:$F$15))/G10) | J10: =IF(B10="","",((B10-MIN($B$6:$B$15))/(MAX($B$6:$B$15)-MIN($B$6:$B$15))*100)) -> 61.096557 | K10: =IF(F10="","",((F10-MIN($F$6:$F$15))/(MAX($F$6:$F$15)-MIN($F$6:$F$15))*100)) -> 86.185987 | L10: =IF(E10="","",((E10-MIN($E$6:$E$15))/(MAX($E$6:$E$15)-MIN($E$6:$E$15))*100)) -> 46.964933 | M10: =IF(I10="","",((I10-MIN($I$6:$I$15))/(MAX($I$6:$I$15)-MIN($I$6:$I$15))*100)) | N10: =IF(H10="","",100-((H10-MIN($H$6:$H$15))/(MAX($H$6:$H$15)-MIN($H$6:$H$15))*100)) | O10: =(IF(ISNUMBER(J10),J10,Inputs!$B$4)*INDEX(Inputs!$B$9:$F$13,MATCH(Inputs!$B$3,Inputs!$A$9:$A$13,0),1)+IF(ISNUMBER(K10),K10,Inputs!$B$4)*INDEX(Inputs!$B$9:$F$13,MATCH(Inputs!$B$3,Inputs!$A$9:$A$13,0),2)+IF(ISNUMBER(L10),L10,Inputs!$B$4)*INDEX(Inputs!$B$9:$F$13,MATCH(Inputs!$B$3,Inputs!$A$9:$A$13,0),3)+IF(ISNUMBER(M10),M10,Inputs!$B$4)*INDEX(Inputs!$B$9:$F$13,MATCH(Inputs!$B$3,Inputs!$A$9:$A$13,0),4)+IF(ISNUMBER(N10),N10,Inputs!$B$4)*INDEX(Inputs!$B$9:$F$13,MATCH(Inputs!$B$3,Inputs!$A$9:$A$13,0),5))/INDEX(Inputs!$G$9:$G$13,MATCH(Inputs!$B$3,Inputs!$A$9:$A$13,0)) -> 60.810548 | P10: =RANK(O10,$O$6:$O$15) -> 3 | Q10: =IF(P10<=Inputs!$B$5,"Lead",IF(P10<=Inputs!$B$6,"Grow","Selective")) -> Lead | R10: =IF(G10="","Growth only (credit neutral)","Growth + credit") -> Growth only (credit neutral)
A11: Health | B11: =SUMIFS(GDP!$E$5:$E$21,GDP!$B$5:$B$21,$A11) -> 257935 | C11: =B11/GDP!$E$22*100 -> 2.4634652 | D11: =B11/SUMIFS(GDP!$D$5:$D$21,GDP!$B$5:$B$21,$A11)*100-100 -> 5.5250992 | E11: =((B11/SUMIFS(GDP!$C$5:$C$21,GDP!$B$5:$B$21,$A11))^(1/4)-1)*100 -> 4.8367026 | F11: =SUMIFS(GDP!$G$5:$G$21,GDP!$B$5:$B$21,$A11)/SUMIFS(GDP!$F$5:$F$21,GDP!$B$5:$B$21,$A11)*100-100 -> 4.3111255 | G11: =IF(SUMIFS(Credit_Map!$C$5:$C$15,Credit_Map!$A$5:$A$15,$A11)=0,"",SUMIFS(Credit_Map!$C$5:$C$15,Credit_Map!$A$5:$A$15,$A11)) | H11: =IF(G11="","",SUMIFS(Credit_Map!$D$5:$D$15,Credit_Map!$A$5:$A$15,$A11)/G11*100) | I11: =IF(G11="","",SUMPRODUCT((Credit_Map!$A$5:$A$15=$A11)*Credit_Map!$C$5:$C$15*(Credit_Map!$E$5:$E$15-Credit_Map!$F$5:$F$15))/G11) | J11: =IF(B11="","",((B11-MIN($B$6:$B$15))/(MAX($B$6:$B$15)-MIN($B$6:$B$15))*100)) -> 0 | K11: =IF(F11="","",((F11-MIN($F$6:$F$15))/(MAX($F$6:$F$15)-MIN($F$6:$F$15))*100)) -> 26.598122 | L11: =IF(E11="","",((E11-MIN($E$6:$E$15))/(MAX($E$6:$E$15)-MIN($E$6:$E$15))*100)) -> 36.583054 | M11: =IF(I11="","",((I11-MIN($I$6:$I$15))/(MAX($I$6:$I$15)-MIN($I$6:$I$15))*100)) | N11: =IF(H11="","",100-((H11-MIN($H$6:$H$15))/(MAX($H$6:$H$15)-MIN($H$6:$H$15))*100)) | O11: =(IF(ISNUMBER(J11),J11,Inputs!$B$4)*INDEX(Inputs!$B$9:$F$13,MATCH(Inputs!$B$3,Inputs!$A$9:$A$13,0),1)+IF(ISNUMBER(K11),K11,Inputs!$B$4)*INDEX(Inputs!$B$9:$F$13,MATCH(Inputs!$B$3,Inputs!$A$9:$A$13,0),2)+IF(ISNUMBER(L11),L11,Inputs!$B$4)*INDEX(Inputs!$B$9:$F$13,MATCH(Inputs!$B$3,Inputs!$A$9:$A$13,0),3)+IF(ISNUMBER(M11),M11,Inputs!$B$4)*INDEX(Inputs!$B$9:$F$13,MATCH(Inputs!$B$3,Inputs!$A$9:$A$13,0),4)+IF(ISNUMBER(N11),N11,Inputs!$B$4)*INDEX(Inputs!$B$9:$F$13,MATCH(Inputs!$B$3,Inputs!$A$9:$A$13,0),5))/INDEX(Inputs!$G$9:$G$13,MATCH(Inputs!$B$3,Inputs!$A$9:$A$13,0)) -> 32.136989 | P11: =RANK(O11,$O$6:$O$15) -> 8 | Q11: =IF(P11<=Inputs!$B$5,"Lead",IF(P11<=Inputs!$B$6,"Grow","Selective")) -> Selective | R11: =IF(G11="","Growth only (credit neutral)","Growth + credit") -> Growth only (credit neutral)
A12: Consumer & Retail | B12: =SUMIFS(GDP!$E$5:$E$21,GDP!$B$5:$B$21,$A12) -> 1105605 | C12: =B12/GDP!$E$22*100 -> 10.559325 | D12: =B12/SUMIFS(GDP!$D$5:$D$21,GDP!$B$5:$B$21,$A12)*100-100 -> 5.5367401 | E12: =((B12/SUMIFS(GDP!$C$5:$C$21,GDP!$B$5:$B$21,$A12))^(1/4)-1)*100 -> 6.2588958 | F12: =SUMIFS(GDP!$G$5:$G$21,GDP!$B$5:$B$21,$A12)/SUMIFS(GDP!$F$5:$F$21,GDP!$B$5:$B$21,$A12)*100-100 -> 5.8041588 | G12: =IF(SUMIFS(Credit_Map!$C$5:$C$15,Credit_Map!$A$5:$A$15,$A12)=0,"",SUMIFS(Credit_Map!$C$5:$C$15,Credit_Map!$A$5:$A$15,$A12)) -> 956946.1 | H12: =IF(G12="","",SUMIFS(Credit_Map!$D$5:$D$15,Credit_Map!$A$5:$A$15,$A12)/G12*100) -> 20.191461 | I12: =IF(G12="","",SUMPRODUCT((Credit_Map!$A$5:$A$15=$A12)*Credit_Map!$C$5:$C$15*(Credit_Map!$E$5:$E$15-Credit_Map!$F$5:$F$15))/G12) -> 53.164181 | J12: =IF(B12="","",((B12-MIN($B$6:$B$15))/(MAX($B$6:$B$15)-MIN($B$6:$B$15))*100)) -> 50.990644 | K12: =IF(F12="","",((F12-MIN($F$6:$F$15))/(MAX($F$6:$F$15)-MIN($F$6:$F$15))*100)) -> 82.306778 | L12: =IF(E12="","",((E12-MIN($E$6:$E$15))/(MAX($E$6:$E$15)-MIN($E$6:$E$15))*100)) -> 58.100283 | M12: =IF(I12="","",((I12-MIN($I$6:$I$15))/(MAX($I$6:$I$15)-MIN($I$6:$I$15))*100)) -> 100 | N12: =IF(H12="","",100-((H12-MIN($H$6:$H$15))/(MAX($H$6:$H$15)-MIN($H$6:$H$15))*100)) -> 18.798154 | O12: =(IF(ISNUMBER(J12),J12,Inputs!$B$4)*INDEX(Inputs!$B$9:$F$13,MATCH(Inputs!$B$3,Inputs!$A$9:$A$13,0),1)+IF(ISNUMBER(K12),K12,Inputs!$B$4)*INDEX(Inputs!$B$9:$F$13,MATCH(Inputs!$B$3,Inputs!$A$9:$A$13,0),2)+IF(ISNUMBER(L12),L12,Inputs!$B$4)*INDEX(Inputs!$B$9:$F$13,MATCH(Inputs!$B$3,Inputs!$A$9:$A$13,0),3)+IF(ISNUMBER(M12),M12,Inputs!$B$4)*INDEX(Inputs!$B$9:$F$13,MATCH(Inputs!$B$3,Inputs!$A$9:$A$13,0),4)+IF(ISNUMBER(N12),N12,Inputs!$B$4)*INDEX(Inputs!$B$9:$F$13,MATCH(Inputs!$B$3,Inputs!$A$9:$A$13,0),5))/INDEX(Inputs!$G$9:$G$13,MATCH(Inputs!$B$3,Inputs!$A$9:$A$13,0)) -> 63.249496 | P12: =RANK(O12,$O$6:$O$15) -> 2 | Q12: =IF(P12<=Inputs!$B$5,"Lead",IF(P12<=Inputs!$B$6,"Grow","Selective")) -> Lead | R12: =IF(G12="","Growth only (credit neutral)","Growth + credit") -> Growth + credit
A13: Agribusiness | B13: =SUMIFS(GDP!$E$5:$E$21,GDP!$B$5:$B$21,$A13) -> 1920338 | C13: =B13/GDP!$E$22*100 -> 18.340612 | D13: =B13/SUMIFS(GDP!$D$5:$D$21,GDP!$B$5:$B$21,$A13)*100-100 -> 3.1042888 | E13: =((B13/SUMIFS(GDP!$C$5:$C$21,GDP!$B$5:$B$21,$A13))^(1/4)-1)*100 -> 3.0943363 | F13: =SUMIFS(GDP!$G$5:$G$21,GDP!$B$5:$B$21,$A13)/SUMIFS(GDP!$F$5:$F$21,GDP!$B$5:$B$21,$A13)*100-100 -> 4.9338745 | G13: =IF(SUMIFS(Credit_Map!$C$5:$C$15,Credit_Map!$A$5:$A$15,$A13)=0,"",SUMIFS(Credit_Map!$C$5:$C$15,Credit_Map!$A$5:$A$15,$A13)) -> 197895.5 | H13: =IF(G13="","",SUMIFS(Credit_Map!$D$5:$D$15,Credit_Map!$A$5:$A$15,$A13)/G13*100) -> 19.270069 | I13: =IF(G13="","",SUMPRODUCT((Credit_Map!$A$5:$A$15=$A13)*Credit_Map!$C$5:$C$15*(Credit_Map!$E$5:$E$15-Credit_Map!$F$5:$F$15))/G13) -> 19 | J13: =IF(B13="","",((B13-MIN($B$6:$B$15))/(MAX($B$6:$B$15)-MIN($B$6:$B$15))*100)) -> 100 | K13: =IF(F13="","",((F13-MIN($F$6:$F$15))/(MAX($F$6:$F$15)-MIN($F$6:$F$15))*100)) -> 49.83438 | L13: =IF(E13="","",((E13-MIN($E$6:$E$15))/(MAX($E$6:$E$15)-MIN($E$6:$E$15))*100)) -> 10.221731 | M13: =IF(I13="","",((I13-MIN($I$6:$I$15))/(MAX($I$6:$I$15)-MIN($I$6:$I$15))*100)) -> 24.355584 | N13: =IF(H13="","",100-((H13-MIN($H$6:$H$15))/(MAX($H$6:$H$15)-MIN($H$6:$H$15))*100)) -> 23.215433 | O13: =(IF(ISNUMBER(J13),J13,Inputs!$B$4)*INDEX(Inputs!$B$9:$F$13,MATCH(Inputs!$B$3,Inputs!$A$9:$A$13,0),1)+IF(ISNUMBER(K13),K13,Inputs!$B$4)*INDEX(Inputs!$B$9:$F$13,MATCH(Inputs!$B$3,Inputs!$A$9:$A$13,0),2)+IF(ISNUMBER(L13),L13,Inputs!$B$4)*INDEX(Inputs!$B$9:$F$13,MATCH(Inputs!$B$3,Inputs!$A$9:$A$13,0),3)+IF(ISNUMBER(M13),M13,Inputs!$B$4)*INDEX(Inputs!$B$9:$F$13,MATCH(Inputs!$B$3,Inputs!$A$9:$A$13,0),4)+IF(ISNUMBER(N13),N13,Inputs!$B$4)*INDEX(Inputs!$B$9:$F$13,MATCH(Inputs!$B$3,Inputs!$A$9:$A$13,0),5))/INDEX(Inputs!$G$9:$G$13,MATCH(Inputs!$B$3,Inputs!$A$9:$A$13,0)) -> 43.506058 | P13: =RANK(O13,$O$6:$O$15) -> 5 | Q13: =IF(P13<=Inputs!$B$5,"Lead",IF(P13<=Inputs!$B$6,"Grow","Selective")) -> Grow | R13: =IF(G13="","Growth only (credit neutral)","Growth + credit") -> Growth + credit
A14: Real Estate & Construction | B14: =SUMIFS(GDP!$E$5:$E$21,GDP!$B$5:$B$21,$A14) -> 1794502 | C14: =B14/GDP!$E$22*100 -> 17.138787 | D14: =B14/SUMIFS(GDP!$D$5:$D$21,GDP!$B$5:$B$21,$A14)*100-100 -> 4.8998615 | E14: =((B14/SUMIFS(GDP!$C$5:$C$21,GDP!$B$5:$B$21,$A14))^(1/4)-1)*100 -> 4.5163781 | F14: =SUMIFS(GDP!$G$5:$G$21,GDP!$B$5:$B$21,$A14)/SUMIFS(GDP!$F$5:$F$21,GDP!$B$5:$B$21,$A14)*100-100 -> 5.5021607 | G14: =IF(SUMIFS(Credit_Map!$C$5:$C$15,Credit_Map!$A$5:$A$15,$A14)=0,"",SUMIFS(Credit_Map!$C$5:$C$15,Credit_Map!$A$5:$A$15,$A14)) -> 686635.9 | H14: =IF(G14="","",SUMIFS(Credit_Map!$D$5:$D$15,Credit_Map!$A$5:$A$15,$A14)/G14*100) -> 24.112532 | I14: =IF(G14="","",SUMPRODUCT((Credit_Map!$A$5:$A$15=$A14)*Credit_Map!$C$5:$C$15*(Credit_Map!$E$5:$E$15-Credit_Map!$F$5:$F$15))/G14) -> 9.2024108 | J14: =IF(B14="","",((B14-MIN($B$6:$B$15))/(MAX($B$6:$B$15)-MIN($B$6:$B$15))*100)) -> 92.430476 | K14: =IF(F14="","",((F14-MIN($F$6:$F$15))/(MAX($F$6:$F$15)-MIN($F$6:$F$15))*100)) -> 71.038504 | L14: =IF(E14="","",((E14-MIN($E$6:$E$15))/(MAX($E$6:$E$15)-MIN($E$6:$E$15))*100)) -> 31.736669 | M14: =IF(I14="","",((I14-MIN($I$6:$I$15))/(MAX($I$6:$I$15)-MIN($I$6:$I$15))*100)) -> 2.6623106 | N14: =IF(H14="","",100-((H14-MIN($H$6:$H$15))/(MAX($H$6:$H$15)-MIN($H$6:$H$15))*100)) -> 0 | O14: =(IF(ISNUMBER(J14),J14,Inputs!$B$4)*INDEX(Inputs!$B$9:$F$13,MATCH(Inputs!$B$3,Inputs!$A$9:$A$13,0),1)+IF(ISNUMBER(K14),K14,Inputs!$B$4)*INDEX(Inputs!$B$9:$F$13,MATCH(Inputs!$B$3,Inputs!$A$9:$A$13,0),2)+IF(ISNUMBER(L14),L14,Inputs!$B$4)*INDEX(Inputs!$B$9:$F$13,MATCH(Inputs!$B$3,Inputs!$A$9:$A$13,0),3)+IF(ISNUMBER(M14),M14,Inputs!$B$4)*INDEX(Inputs!$B$9:$F$13,MATCH(Inputs!$B$3,Inputs!$A$9:$A$13,0),4)+IF(ISNUMBER(N14),N14,Inputs!$B$4)*INDEX(Inputs!$B$9:$F$13,MATCH(Inputs!$B$3,Inputs!$A$9:$A$13,0),5))/INDEX(Inputs!$G$9:$G$13,MATCH(Inputs!$B$3,Inputs!$A$9:$A$13,0)) -> 41.538684 | P14: =RANK(O14,$O$6:$O$15) -> 6 | Q14: =IF(P14<=Inputs!$B$5,"Lead",IF(P14<=Inputs!$B$6,"Grow","Selective")) -> Grow | R14: =IF(G14="","Growth only (credit neutral)","Growth + credit") -> Growth + credit
A15: Manufacturing | B15: =SUMIFS(GDP!$E$5:$E$21,GDP!$B$5:$B$21,$A15) -> 892166 | C15: =B15/GDP!$E$22*100 -> 8.5208283 | D15: =B15/SUMIFS(GDP!$D$5:$D$21,GDP!$B$5:$B$21,$A15)*100-100 -> 1.9762801 | E15: =((B15/SUMIFS(GDP!$C$5:$C$21,GDP!$B$5:$B$21,$A15))^(1/4)-1)*100 -> 2.4187254 | F15: =SUMIFS(GDP!$G$5:$G$21,GDP!$B$5:$B$21,$A15)/SUMIFS(GDP!$F$5:$F$21,GDP!$B$5:$B$21,$A15)*100-100 -> 4.4158346 | G15: =IF(SUMIFS(Credit_Map!$C$5:$C$15,Credit_Map!$A$5:$A$15,$A15)=0,"",SUMIFS(Credit_Map!$C$5:$C$15,Credit_Map!$A$5:$A$15,$A15)) -> 584989.3 | H15: =IF(G15="","",SUMIFS(Credit_Map!$D$5:$D$15,Credit_Map!$A$5:$A$15,$A15)/G15*100) -> 18.398559 | I15: =IF(G15="","",SUMPRODUCT((Credit_Map!$A$5:$A$15=$A15)*Credit_Map!$C$5:$C$15*(Credit_Map!$E$5:$E$15-Credit_Map!$F$5:$F$15))/G15) -> 30 | J15: =IF(B15="","",((B15-MIN($B$6:$B$15))/(MAX($B$6:$B$15)-MIN($B$6:$B$15))*100)) -> 38.151459 | K15: =IF(F15="","",((F15-MIN($F$6:$F$15))/(MAX($F$6:$F$15)-MIN($F$6:$F$15))*100)) -> 30.505068 | L15: =IF(E15="","",((E15-MIN($E$6:$E$15))/(MAX($E$6:$E$15)-MIN($E$6:$E$15))*100)) -> 0 | M15: =IF(I15="","",((I15-MIN($I$6:$I$15))/(MAX($I$6:$I$15)-MIN($I$6:$I$15))*100)) -> 48.711168 | N15: =IF(H15="","",100-((H15-MIN($H$6:$H$15))/(MAX($H$6:$H$15)-MIN($H$6:$H$15))*100)) -> 27.393575 | O15: =(IF(ISNUMBER(J15),J15,Inputs!$B$4)*INDEX(Inputs!$B$9:$F$13,MATCH(Inputs!$B$3,Inputs!$A$9:$A$13,0),1)+IF(ISNUMBER(K15),K15,Inputs!$B$4)*INDEX(Inputs!$B$9:$F$13,MATCH(Inputs!$B$3,Inputs!$A$9:$A$13,0),2)+IF(ISNUMBER(L15),L15,Inputs!$B$4)*INDEX(Inputs!$B$9:$F$13,MATCH(Inputs!$B$3,Inputs!$A$9:$A$13,0),3)+IF(ISNUMBER(M15),M15,Inputs!$B$4)*INDEX(Inputs!$B$9:$F$13,MATCH(Inputs!$B$3,Inputs!$A$9:$A$13,0),4)+IF(ISNUMBER(N15),N15,Inputs!$B$4)*INDEX(Inputs!$B$9:$F$13,MATCH(Inputs!$B$3,Inputs!$A$9:$A$13,0),5))/INDEX(Inputs!$G$9:$G$13,MATCH(Inputs!$B$3,Inputs!$A$9:$A$13,0)) -> 30.477508 | P15: =RANK(O15,$O$6:$O$15) -> 9 | Q15: =IF(P15<=Inputs!$B$5,"Lead",IF(P15<=Inputs!$B$6,"Grow","Selective")) -> Selective | R15: =IF(G15="","Growth only (credit neutral)","Growth + credit") -> Growth + credit
A37: Reading the table: growth and size say where the economy is moving; credit demand and NPLs say where banks see client activity and risk. Public Sector and Health have no matching bank sector, so their credit pillars are neutral.

Sheet Scenarios
A1: Scores and ranks under five weighting scenarios
A2: A robust priority stays near the top whatever the weights. Rank range shows sensitivity.
A4: Industry group | B4: Score: Balanced | C4: Score: Growth-led | D4: Score: Risk-aware | E4: Score: Scale-led | F4: Score: Equal | G4: Rank: Balanced | H4: Rank: Growth-led | I4: Rank: Risk-aware | J4: Rank: Scale-led | K4: Rank: Equal | L4: Best rank | M4: Worst rank | N4: Stability
A5: =Scorecard!A6 -> Financial Services | B5: =(IF(ISNUMBER(Scorecard!J6),Scorecard!J6,Inputs!$B$4)*Inputs!B$9+IF(ISNUMBER(Scorecard!K6),Scorecard!K6,Inputs!$B$4)*Inputs!C$9+IF(ISNUMBER(Scorecard!L6),Scorecard!L6,Inputs!$B$4)*Inputs!D$9+IF(ISNUMBER(Scorecard!M6),Scorecard!M6,Inputs!$B$4)*Inputs!E$9+IF(ISNUMBER(Scorecard!N6),Scorecard!N6,Inputs!$B$4)*Inputs!F$9)/Inputs!$G$9 -> 76.746877 | C5: =(IF(ISNUMBER(Scorecard!J6),Scorecard!J6,Inputs!$B$4)*Inputs!B$10+IF(ISNUMBER(Scorecard!K6),Scorecard!K6,Inputs!$B$4)*Inputs!C$10+IF(ISNUMBER(Scorecard!L6),Scorecard!L6,Inputs!$B$4)*Inputs!D$10+IF(ISNUMBER(Scorecard!M6),Scorecard!M6,Inputs!$B$4)*Inputs!E$10+IF(ISNUMBER(Scorecard!N6),Scorecard!N6,Inputs!$B$4)*Inputs!F$10)/Inputs!$G$10 -> 81.47324 | D5: =(IF(ISNUMBER(Scorecard!J6),Scorecard!J6,Inputs!$B$4)*Inputs!B$11+IF(ISNUMBER(Scorecard!K6),Scorecard!K6,Inputs!$B$4)*Inputs!C$11+IF(ISNUMBER(Scorecard!L6),Scorecard!L6,Inputs!$B$4)*Inputs!D$11+IF(ISNUMBER(Scorecard!M6),Scorecard!M6,Inputs!$B$4)*Inputs!E$11+IF(ISNUMBER(Scorecard!N6),Scorecard!N6,Inputs!$B$4)*Inputs!F$11)/Inputs!$G$11 -> 80.196976 | E5: =(IF(ISNUMBER(Scorecard!J6),Scorecard!J6,Inputs!$B$4)*Inputs!B$12+IF(ISNUMBER(Scorecard!K6),Scorecard!K6,Inputs!$B$4)*Inputs!C$12+IF(ISNUMBER(Scorecard!L6),Scorecard!L6,Inputs!$B$4)*Inputs!D$12+IF(ISNUMBER(Scorecard!M6),Scorecard!M6,Inputs!$B$4)*Inputs!E$12+IF(ISNUMBER(Scorecard!N6),Scorecard!N6,Inputs!$B$4)*Inputs!F$12)/Inputs!$G$12 -> 68.381069 | F5: =(IF(ISNUMBER(Scorecard!J6),Scorecard!J6,Inputs!$B$4)*Inputs!B$13+IF(ISNUMBER(Scorecard!K6),Scorecard!K6,Inputs!$B$4)*Inputs!C$13+IF(ISNUMBER(Scorecard!L6),Scorecard!L6,Inputs!$B$4)*Inputs!D$13+IF(ISNUMBER(Scorecard!M6),Scorecard!M6,Inputs!$B$4)*Inputs!E$13+IF(ISNUMBER(Scorecard!N6),Scorecard!N6,Inputs!$B$4)*Inputs!F$13)/Inputs!$G$13 -> 76.746877 | G5: =RANK(B5,B$5:B$14) -> 1 | H5: =RANK(C5,C$5:C$14) -> 1 | I5: =RANK(D5,D$5:D$14) -> 1 | J5: =RANK(E5,E$5:E$14) -> 1 | K5: =RANK(F5,F$5:F$14) -> 1 | L5: =MIN(G5:K5) -> 1 | M5: =MAX(G5:K5) -> 1 | N5: =IF(M5-L5<=3,"Stable","Sensitive") -> Stable
A6: =Scorecard!A7 -> Energy & Resources | B6: =(IF(ISNUMBER(Scorecard!J7),Scorecard!J7,Inputs!$B$4)*Inputs!B$9+IF(ISNUMBER(Scorecard!K7),Scorecard!K7,Inputs!$B$4)*Inputs!C$9+IF(ISNUMBER(Scorecard!L7),Scorecard!L7,Inputs!$B$4)*Inputs!D$9+IF(ISNUMBER(Scorecard!M7),Scorecard!M7,Inputs!$B$4)*Inputs!E$9+IF(ISNUMBER(Scorecard!N7),Scorecard!N7,Inputs!$B$4)*Inputs!F$9)/Inputs!$G$9 -> 45.253634 | C6: =(IF(ISNUMBER(Scorecard!J7),Scorecard!J7,Inputs!$B$4)*Inputs!B$10+IF(ISNUMBER(Scorecard!K7),Scorecard!K7,Inputs!$B$4)*Inputs!C$10+IF(ISNUMBER(Scorecard!L7),Scorecard!L7,Inputs!$B$4)*Inputs!D$10+IF(ISNUMBER(Scorecard!M7),Scorecard!M7,Inputs!$B$4)*Inputs!E$10+IF(ISNUMBER(Scorecard!N7),Scorecard!N7,Inputs!$B$4)*Inputs!F$10)/Inputs!$G$10 -> 46.880818 | D6: =(IF(ISNUMBER(Scorecard!J7),Scorecard!J7,Inputs!$B$4)*Inputs!B$11+IF(ISNUMBER(Scorecard!K7),Scorecard!K7,Inputs!$B$4)*Inputs!C$11+IF(ISNUMBER(Scorecard!L7),Scorecard!L7,Inputs!$B$4)*Inputs!D$11+IF(ISNUMBER(Scorecard!M7),Scorecard!M7,Inputs!$B$4)*Inputs!E$11+IF(ISNUMBER(Scorecard!N7),Scorecard!N7,Inputs!$B$4)*Inputs!F$11)/Inputs!$G$11 -> 48.662768 | E6: =(IF(ISNUMBER(Scorecard!J7),Scorecard!J7,Inputs!$B$4)*Inputs!B$12+IF(ISNUMBER(Scorecard!K7),Scorecard!K7,Inputs!$B$4)*Inputs!C$12+IF(ISNUMBER(Scorecard!L7),Scorecard!L7,Inputs!$B$4)*Inputs!D$12+IF(ISNUMBER(Scorecard!M7),Scorecard!M7,Inputs!$B$4)*Inputs!E$12+IF(ISNUMBER(Scorecard!N7),Scorecard!N7,Inputs!$B$4)*Inputs!F$12)/Inputs!$G$12 -> 33.127225 | F6: =(IF(ISNUMBER(Scorecard!J7),Scorecard!J7,Inputs!$B$4)*Inputs!B$13+IF(ISNUMBER(Scorecard!K7),Scorecard!K7,Inputs!$B$4)*Inputs!C$13+IF(ISNUMBER(Scorecard!L7),Scorecard!L7,Inputs!$B$4)*Inputs!D$13+IF(ISNUMBER(Scorecard!M7),Scorecard!M7,Inputs!$B$4)*Inputs!E$13+IF(ISNUMBER(Scorecard!N7),Scorecard!N7,Inputs!$B$4)*Inputs!F$13)/Inputs!$G$13 -> 42.197172 | G6: =RANK(B6,B$5:B$14) -> 4 | H6: =RANK(C6,C$5:C$14) -> 4 | I6: =RANK(D6,D$5:D$14) -> 4 | J6: =RANK(E6,E$5:E$14) -> 7 | K6: =RANK(F6,F$5:F$14) -> 4 | L6: =MIN(G6:K6) -> 4 | M6: =MAX(G6:K6) -> 7 | N6: =IF(M6-L6<=3,"Stable","Sensitive") -> Stable
A7: =Scorecard!A8 -> Technology, Media & Telecom | B7: =(IF(ISNUMBER(Scorecard!J8),Scorecard!J8,Inputs!$B$4)*Inputs!B$9+IF(ISNUMBER(Scorecard!K8),Scorecard!K8,Inputs!$B$4)*Inputs!C$9+IF(ISNUMBER(Scorecard!L8),Scorecard!L8,Inputs!$B$4)*Inputs!D$9+IF(ISNUMBER(Scorecard!M8),Scorecard!M8,Inputs!$B$4)*Inputs!E$9+IF(ISNUMBER(Scorecard!N8),Scorecard!N8,Inputs!$B$4)*Inputs!F$9)/Inputs!$G$9 -> 33.893572 | C7: =(IF(ISNUMBER(Scorecard!J8),Scorecard!J8,Inputs!$B$4)*Inputs!B$10+IF(ISNUMBER(Scorecard!K8),Scorecard!K8,Inputs!$B$4)*Inputs!C$10+IF(ISNUMBER(Scorecard!L8),Scorecard!L8,Inputs!$B$4)*Inputs!D$10+IF(ISNUMBER(Scorecard!M8),Scorecard!M8,Inputs!$B$4)*Inputs!E$10+IF(ISNUMBER(Scorecard!N8),Scorecard!N8,Inputs!$B$4)*Inputs!F$10)/Inputs!$G$10 -> 42.739605 | D7: =(IF(ISNUMBER(Scorecard!J8),Scorecard!J8,Inputs!$B$4)*Inputs!B$11+IF(ISNUMBER(Scorecard!K8),Scorecard!K8,Inputs!$B$4)*Inputs!C$11+IF(ISNUMBER(Scorecard!L8),Scorecard!L8,Inputs!$B$4)*Inputs!D$11+IF(ISNUMBER(Scorecard!M8),Scorecard!M8,Inputs!$B$4)*Inputs!E$11+IF(ISNUMBER(Scorecard!N8),Scorecard!N8,Inputs!$B$4)*Inputs!F$11)/Inputs!$G$11 -> 31.930236 | E7: =(IF(ISNUMBER(Scorecard!J8),Scorecard!J8,Inputs!$B$4)*Inputs!B$12+IF(ISNUMBER(Scorecard!K8),Scorecard!K8,Inputs!$B$4)*Inputs!C$12+IF(ISNUMBER(Scorecard!L8),Scorecard!L8,Inputs!$B$4)*Inputs!D$12+IF(ISNUMBER(Scorecard!M8),Scorecard!M8,Inputs!$B$4)*Inputs!E$12+IF(ISNUMBER(Scorecard!N8),Scorecard!N8,Inputs!$B$4)*Inputs!F$12)/Inputs!$G$12 -> 24.89486 | F7: =(IF(ISNUMBER(Scorecard!J8),Scorecard!J8,Inputs!$B$4)*Inputs!B$13+IF(ISNUMBER(Scorecard!K8),Scorecard!K8,Inputs!$B$4)*Inputs!C$13+IF(ISNUMBER(Scorecard!L8),Scorecard!L8,Inputs!$B$4)*Inputs!D$13+IF(ISNUMBER(Scorecard!M8),Scorecard!M8,Inputs!$B$4)*Inputs!E$13+IF(ISNUMBER(Scorecard!N8),Scorecard!N8,Inputs!$B$4)*Inputs!F$13)/Inputs!$G$13 -> 35.394807 | G7: =RANK(B7,B$5:B$14) -> 7 | H7: =RANK(C7,C$5:C$14) -> 5 | I7: =RANK(D7,D$5:D$14) -> 8 | J7: =RANK(E7,E$5:E$14) -> 9 | K7: =RANK(F7,F$5:F$14) -> 7 | L7: =MIN(G7:K7) -> 5 | M7: =MAX(G7:K7) -> 9 | N7: =IF(M7-L7<=3,"Stable","Sensitive") -> Sensitive
A8: =Scorecard!A9 -> Transport & Logistics | B8: =(IF(ISNUMBER(Scorecard!J9),Scorecard!J9,Inputs!$B$4)*Inputs!B$9+IF(ISNUMBER(Scorecard!K9),Scorecard!K9,Inputs!$B$4)*Inputs!C$9+IF(ISNUMBER(Scorecard!L9),Scorecard!L9,Inputs!$B$4)*Inputs!D$9+IF(ISNUMBER(Scorecard!M9),Scorecard!M9,Inputs!$B$4)*Inputs!E$9+IF(ISNUMBER(Scorecard!N9),Scorecard!N9,Inputs!$B$4)*Inputs!F$9)/Inputs!$G$9 -> 22.56725 | C8: =(IF(ISNUMBER(Scorecard!J9),Scorecard!J9,Inputs!$B$4)*Inputs!B$10+IF(ISNUMBER(Scorecard!K9),Scorecard!K9,Inputs!$B$4)*Inputs!C$10+IF(ISNUMBER(Scorecard!L9),Scorecard!L9,Inputs!$B$4)*Inputs!D$10+IF(ISNUMBER(Scorecard!M9),Scorecard!M9,Inputs!$B$4)*Inputs!E$10+IF(ISNUMBER(Scorecard!N9),Scorecard!N9,Inputs!$B$4)*Inputs!F$10)/Inputs!$G$10 -> 17.666664 | D8: =(IF(ISNUMBER(Scorecard!J9),Scorecard!J9,Inputs!$B$4)*Inputs!B$11+IF(ISNUMBER(Scorecard!K9),Scorecard!K9,Inputs!$B$4)*Inputs!C$11+IF(ISNUMBER(Scorecard!L9),Scorecard!L9,Inputs!$B$4)*Inputs!D$11+IF(ISNUMBER(Scorecard!M9),Scorecard!M9,Inputs!$B$4)*Inputs!E$11+IF(ISNUMBER(Scorecard!N9),Scorecard!N9,Inputs!$B$4)*Inputs!F$11)/Inputs!$G$11 -> 27.98336 | E8: =(IF(ISNUMBER(Scorecard!J9),Scorecard!J9,Inputs!$B$4)*Inputs!B$12+IF(ISNUMBER(Scorecard!K9),Scorecard!K9,Inputs!$B$4)*Inputs!C$12+IF(ISNUMBER(Scorecard!L9),Scorecard!L9,Inputs!$B$4)*Inputs!D$12+IF(ISNUMBER(Scorecard!M9),Scorecard!M9,Inputs!$B$4)*Inputs!E$12+IF(ISNUMBER(Scorecard!N9),Scorecard!N9,Inputs!$B$4)*Inputs!F$12)/Inputs!$G$12 -> 31.253863 | F8: =(IF(ISNUMBER(Scorecard!J9),Scorecard!J9,Inputs!$B$4)*Inputs!B$13+IF(ISNUMBER(Scorecard!K9),Scorecard!K9,Inputs!$B$4)*Inputs!C$13+IF(ISNUMBER(Scorecard!L9),Scorecard!L9,Inputs!$B$4)*Inputs!D$13+IF(ISNUMBER(Scorecard!M9),Scorecard!M9,Inputs!$B$4)*Inputs!E$13+IF(ISNUMBER(Scorecard!N9),Scorecard!N9,Inputs!$B$4)*Inputs!F$13)/Inputs!$G$13 -> 24.390975 | G8: =RANK(B8,B$5:B$14) -> 10 | H8: =RANK(C8,C$5:C$14) -> 10 | I8: =RANK(D8,D$5:D$14) -> 10 | J8: =RANK(E8,E$5:E$14) -> 8 | K8: =RANK(F8,F$5:F$14) -> 10 | L8: =MIN(G8:K8) -> 8 | M8: =MAX(G8:K8) -> 10 | N8: =IF(M8-L8<=3,"Stable","Sensitive") -> Stable
A9: =Scorecard!A10 -> Public Sector & Development | B9: =(IF(ISNUMBER(Scorecard!J10),Scorecard!J10,Inputs!$B$4)*Inputs!B$9+IF(ISNUMBER(Scorecard!K10),Scorecard!K10,Inputs!$B$4)*Inputs!C$9+IF(ISNUMBER(Scorecard!L10),Scorecard!L10,Inputs!$B$4)*Inputs!D$9+IF(ISNUMBER(Scorecard!M10),Scorecard!M10,Inputs!$B$4)*Inputs!E$9+IF(ISNUMBER(Scorecard!N10),Scorecard!N10,Inputs!$B$4)*Inputs!F$9)/Inputs!$G$9 -> 60.810548 | C9: =(IF(ISNUMBER(Scorecard!J10),Scorecard!J10,Inputs!$B$4)*Inputs!B$10+IF(ISNUMBER(Scorecard!K10),Scorecard!K10,Inputs!$B$4)*Inputs!C$10+IF(ISNUMBER(Scorecard!L10),Scorecard!L10,Inputs!$B$4)*Inputs!D$10+IF(ISNUMBER(Scorecard!M10),Scorecard!M10,Inputs!$B$4)*Inputs!E$10+IF(ISNUMBER(Scorecard!N10),Scorecard!N10,Inputs!$B$4)*Inputs!F$10)/Inputs!$G$10 -> 63.015984 | D9: =(IF(ISNUMBER(Scorecard!J10),Scorecard!J10,Inputs!$B$4)*Inputs!B$11+IF(ISNUMBER(Scorecard!K10),Scorecard!K10,Inputs!$B$4)*Inputs!C$11+IF(ISNUMBER(Scorecard!L10),Scorecard!L10,Inputs!$B$4)*Inputs!D$11+IF(ISNUMBER(Scorecard!M10),Scorecard!M10,Inputs!$B$4)*Inputs!E$11+IF(ISNUMBER(Scorecard!N10),Scorecard!N10,Inputs!$B$4)*Inputs!F$11)/Inputs!$G$11 -> 57.343703 | E9: =(IF(ISNUMBER(Scorecard!J10),Scorecard!J10,Inputs!$B$4)*Inputs!B$12+IF(ISNUMBER(Scorecard!K10),Scorecard!K10,Inputs!$B$4)*Inputs!C$12+IF(ISNUMBER(Scorecard!L10),Scorecard!L10,Inputs!$B$4)*Inputs!D$12+IF(ISNUMBER(Scorecard!M10),Scorecard!M10,Inputs!$B$4)*Inputs!E$12+IF(ISNUMBER(Scorecard!N10),Scorecard!N10,Inputs!$B$4)*Inputs!F$12)/Inputs!$G$12 -> 60.117842 | F9: =(IF(ISNUMBER(Scorecard!J10),Scorecard!J10,Inputs!$B$4)*Inputs!B$13+IF(ISNUMBER(Scorecard!K10),Scorecard!K10,Inputs!$B$4)*Inputs!C$13+IF(ISNUMBER(Scorecard!L10),Scorecard!L10,Inputs!$B$4)*Inputs!D$13+IF(ISNUMBER(Scorecard!M10),Scorecard!M10,Inputs!$B$4)*Inputs!E$13+IF(ISNUMBER(Scorecard!N10),Scorecard!N10,Inputs!$B$4)*Inputs!F$13)/Inputs!$G$13 -> 58.849495 | G9: =RANK(B9,B$5:B$14) -> 3 | H9: =RANK(C9,C$5:C$14) -> 3 | I9: =RANK(D9,D$5:D$14) -> 2 | J9: =RANK(E9,E$5:E$14) -> 3 | K9: =RANK(F9,F$5:F$14) -> 3 | L9: =MIN(G9:K9) -> 2 | M9: =MAX(G9:K9) -> 3 | N9: =IF(M9-L9<=3,"Stable","Sensitive") -> Stable
A10: =Scorecard!A11 -> Health | B10: =(IF(ISNUMBER(Scorecard!J11),Scorecard!J11,Inputs!$B$4)*Inputs!B$9+IF(ISNUMBER(Scorecard!K11),Scorecard!K11,Inputs!$B$4)*Inputs!C$9+IF(ISNUMBER(Scorecard!L11),Scorecard!L11,Inputs!$B$4)*Inputs!D$9+IF(ISNUMBER(Scorecard!M11),Scorecard!M11,Inputs!$B$4)*Inputs!E$9+IF(ISNUMBER(Scorecard!N11),Scorecard!N11,Inputs!$B$4)*Inputs!F$9)/Inputs!$G$9 -> 32.136989 | C10: =(IF(ISNUMBER(Scorecard!J11),Scorecard!J11,Inputs!$B$4)*Inputs!B$10+IF(ISNUMBER(Scorecard!K11),Scorecard!K11,Inputs!$B$4)*Inputs!C$10+IF(ISNUMBER(Scorecard!L11),Scorecard!L11,Inputs!$B$4)*Inputs!D$10+IF(ISNUMBER(Scorecard!M11),Scorecard!M11,Inputs!$B$4)*Inputs!E$10+IF(ISNUMBER(Scorecard!N11),Scorecard!N11,Inputs!$B$4)*Inputs!F$10)/Inputs!$G$10 -> 33.455106 | D10: =(IF(ISNUMBER(Scorecard!J11),Scorecard!J11,Inputs!$B$4)*Inputs!B$11+IF(ISNUMBER(Scorecard!K11),Scorecard!K11,Inputs!$B$4)*Inputs!C$11+IF(ISNUMBER(Scorecard!L11),Scorecard!L11,Inputs!$B$4)*Inputs!D$11+IF(ISNUMBER(Scorecard!M11),Scorecard!M11,Inputs!$B$4)*Inputs!E$11+IF(ISNUMBER(Scorecard!N11),Scorecard!N11,Inputs!$B$4)*Inputs!F$11)/Inputs!$G$11 -> 35.148024 | E10: =(IF(ISNUMBER(Scorecard!J11),Scorecard!J11,Inputs!$B$4)*Inputs!B$12+IF(ISNUMBER(Scorecard!K11),Scorecard!K11,Inputs!$B$4)*Inputs!C$12+IF(ISNUMBER(Scorecard!L11),Scorecard!L11,Inputs!$B$4)*Inputs!D$12+IF(ISNUMBER(Scorecard!M11),Scorecard!M11,Inputs!$B$4)*Inputs!E$12+IF(ISNUMBER(Scorecard!N11),Scorecard!N11,Inputs!$B$4)*Inputs!F$12)/Inputs!$G$12 -> 22.648024 | F10: =(IF(ISNUMBER(Scorecard!J11),Scorecard!J11,Inputs!$B$4)*Inputs!B$13+IF(ISNUMBER(Scorecard!K11),Scorecard!K11,Inputs!$B$4)*Inputs!C$13+IF(ISNUMBER(Scorecard!L11),Scorecard!L11,Inputs!$B$4)*Inputs!D$13+IF(ISNUMBER(Scorecard!M11),Scorecard!M11,Inputs!$B$4)*Inputs!E$13+IF(ISNUMBER(Scorecard!N11),Scorecard!N11,Inputs!$B$4)*Inputs!F$13)/Inputs!$G$13 -> 32.636235 | G10: =RANK(B10,B$5:B$14) -> 8 | H10: =RANK(C10,C$5:C$14) -> 8 | I10: =RANK(D10,D$5:D$14) -> 6 | J10: =RANK(E10,E$5:E$14) -> 10 | K10: =RANK(F10,F$5:F$14) -> 8 | L10: =MIN(G10:K10) -> 6 | M10: =MAX(G10:K10) -> 10 | N10: =IF(M10-L10<=3,"Stable","Sensitive") -> Sensitive
A11: =Scorecard!A12 -> Consumer & Retail | B11: =(IF(ISNUMBER(Scorecard!J12),Scorecard!J12,Inputs!$B$4)*Inputs!B$9+IF(ISNUMBER(Scorecard!K12),Scorecard!K12,Inputs!$B$4)*Inputs!C$9+IF(ISNUMBER(Scorecard!L12),Scorecard!L12,Inputs!$B$4)*Inputs!D$9+IF(ISNUMBER(Scorecard!M12),Scorecard!M12,Inputs!$B$4)*Inputs!E$9+IF(ISNUMBER(Scorecard!N12),Scorecard!N12,Inputs!$B$4)*Inputs!F$9)/Inputs!$G$9 -> 63.249496 | C11: =(IF(ISNUMBER(Scorecard!J12),Scorecard!J12,Inputs!$B$4)*Inputs!B$10+IF(ISNUMBER(Scorecard!K12),Scorecard!K12,Inputs!$B$4)*Inputs!C$10+IF(ISNUMBER(Scorecard!L12),Scorecard!L12,Inputs!$B$4)*Inputs!D$10+IF(ISNUMBER(Scorecard!M12),Scorecard!M12,Inputs!$B$4)*Inputs!E$10+IF(ISNUMBER(Scorecard!N12),Scorecard!N12,Inputs!$B$4)*Inputs!F$10)/Inputs!$G$10 -> 70.311323 | D11: =(IF(ISNUMBER(Scorecard!J12),Scorecard!J12,Inputs!$B$4)*Inputs!B$11+IF(ISNUMBER(Scorecard!K12),Scorecard!K12,Inputs!$B$4)*Inputs!C$11+IF(ISNUMBER(Scorecard!L12),Scorecard!L12,Inputs!$B$4)*Inputs!D$11+IF(ISNUMBER(Scorecard!M12),Scorecard!M12,Inputs!$B$4)*Inputs!E$11+IF(ISNUMBER(Scorecard!N12),Scorecard!N12,Inputs!$B$4)*Inputs!F$11)/Inputs!$G$11 -> 50.873435 | E11: =(IF(ISNUMBER(Scorecard!J12),Scorecard!J12,Inputs!$B$4)*Inputs!B$12+IF(ISNUMBER(Scorecard!K12),Scorecard!K12,Inputs!$B$4)*Inputs!C$12+IF(ISNUMBER(Scorecard!L12),Scorecard!L12,Inputs!$B$4)*Inputs!D$12+IF(ISNUMBER(Scorecard!M12),Scorecard!M12,Inputs!$B$4)*Inputs!E$12+IF(ISNUMBER(Scorecard!N12),Scorecard!N12,Inputs!$B$4)*Inputs!F$12)/Inputs!$G$12 -> 58.921558 | F11: =(IF(ISNUMBER(Scorecard!J12),Scorecard!J12,Inputs!$B$4)*Inputs!B$13+IF(ISNUMBER(Scorecard!K12),Scorecard!K12,Inputs!$B$4)*Inputs!C$13+IF(ISNUMBER(Scorecard!L12),Scorecard!L12,Inputs!$B$4)*Inputs!D$13+IF(ISNUMBER(Scorecard!M12),Scorecard!M12,Inputs!$B$4)*Inputs!E$13+IF(ISNUMBER(Scorecard!N12),Scorecard!N12,Inputs!$B$4)*Inputs!F$13)/Inputs!$G$13 -> 62.039172 | G11: =RANK(B11,B$5:B$14) -> 2 | H11: =RANK(C11,C$5:C$14) -> 2 | I11: =RANK(D11,D$5:D$14) -> 3 | J11: =RANK(E11,E$5:E$14) -> 4 | K11: =RANK(F11,F$5:F$14) -> 2 | L11: =MIN(G11:K11) -> 2 | M11: =MAX(G11:K11) -> 4 | N11: =IF(M11-L11<=3,"Stable","Sensitive") -> Stable
A12: =Scorecard!A13 -> Agribusiness | B12: =(IF(ISNUMBER(Scorecard!J13),Scorecard!J13,Inputs!$B$4)*Inputs!B$9+IF(ISNUMBER(Scorecard!K13),Scorecard!K13,Inputs!$B$4)*Inputs!C$9+IF(ISNUMBER(Scorecard!L13),Scorecard!L13,Inputs!$B$4)*Inputs!D$9+IF(ISNUMBER(Scorecard!M13),Scorecard!M13,Inputs!$B$4)*Inputs!E$9+IF(ISNUMBER(Scorecard!N13),Scorecard!N13,Inputs!$B$4)*Inputs!F$9)/Inputs!$G$9 -> 43.506058 | C12: =(IF(ISNUMBER(Scorecard!J13),Scorecard!J13,Inputs!$B$4)*Inputs!B$10+IF(ISNUMBER(Scorecard!K13),Scorecard!K13,Inputs!$B$4)*Inputs!C$10+IF(ISNUMBER(Scorecard!L13),Scorecard!L13,Inputs!$B$4)*Inputs!D$10+IF(ISNUMBER(Scorecard!M13),Scorecard!M13,Inputs!$B$4)*Inputs!E$10+IF(ISNUMBER(Scorecard!N13),Scorecard!N13,Inputs!$B$4)*Inputs!F$10)/Inputs!$G$10 -> 37.190126 | D12: =(IF(ISNUMBER(Scorecard!J13),Scorecard!J13,Inputs!$B$4)*Inputs!B$11+IF(ISNUMBER(Scorecard!K13),Scorecard!K13,Inputs!$B$4)*Inputs!C$11+IF(ISNUMBER(Scorecard!L13),Scorecard!L13,Inputs!$B$4)*Inputs!D$11+IF(ISNUMBER(Scorecard!M13),Scorecard!M13,Inputs!$B$4)*Inputs!E$11+IF(ISNUMBER(Scorecard!N13),Scorecard!N13,Inputs!$B$4)*Inputs!F$11)/Inputs!$G$11 -> 41.436841 | E12: =(IF(ISNUMBER(Scorecard!J13),Scorecard!J13,Inputs!$B$4)*Inputs!B$12+IF(ISNUMBER(Scorecard!K13),Scorecard!K13,Inputs!$B$4)*Inputs!C$12+IF(ISNUMBER(Scorecard!L13),Scorecard!L13,Inputs!$B$4)*Inputs!D$12+IF(ISNUMBER(Scorecard!M13),Scorecard!M13,Inputs!$B$4)*Inputs!E$12+IF(ISNUMBER(Scorecard!N13),Scorecard!N13,Inputs!$B$4)*Inputs!F$12)/Inputs!$G$12 -> 60.632983 | F12: =(IF(ISNUMBER(Scorecard!J13),Scorecard!J13,Inputs!$B$4)*Inputs!B$13+IF(ISNUMBER(Scorecard!K13),Scorecard!K13,Inputs!$B$4)*Inputs!C$13+IF(ISNUMBER(Scorecard!L13),Scorecard!L13,Inputs!$B$4)*Inputs!D$13+IF(ISNUMBER(Scorecard!M13),Scorecard!M13,Inputs!$B$4)*Inputs!E$13+IF(ISNUMBER(Scorecard!N13),Scorecard!N13,Inputs!$B$4)*Inputs!F$13)/Inputs!$G$13 -> 41.525426 | G12: =RANK(B12,B$5:B$14) -> 5 | H12: =RANK(C12,C$5:C$14) -> 7 | I12: =RANK(D12,D$5:D$14) -> 5 | J12: =RANK(E12,E$5:E$14) -> 2 | K12: =RANK(F12,F$5:F$14) -> 5 | L12: =MIN(G12:K12) -> 2 | M12: =MAX(G12:K12) -> 7 | N12: =IF(M12-L12<=3,"Stable","Sensitive") -> Sensitive
A13: =Scorecard!A14 -> Real Estate & Construction | B13: =(IF(ISNUMBER(Scorecard!J14),Scorecard!J14,Inputs!$B$4)*Inputs!B$9+IF(ISNUMBER(Scorecard!K14),Scorecard!K14,Inputs!$B$4)*Inputs!C$9+IF(ISNUMBER(Scorecard!L14),Scorecard!L14,Inputs!$B$4)*Inputs!D$9+IF(ISNUMBER(Scorecard!M14),Scorecard!M14,Inputs!$B$4)*Inputs!E$9+IF(ISNUMBER(Scorecard!N14),Scorecard!N14,Inputs!$B$4)*Inputs!F$9)/Inputs!$G$9 -> 41.538684 | C13: =(IF(ISNUMBER(Scorecard!J14),Scorecard!J14,Inputs!$B$4)*Inputs!B$10+IF(ISNUMBER(Scorecard!K14),Scorecard!K14,Inputs!$B$4)*Inputs!C$10+IF(ISNUMBER(Scorecard!L14),Scorecard!L14,Inputs!$B$4)*Inputs!D$10+IF(ISNUMBER(Scorecard!M14),Scorecard!M14,Inputs!$B$4)*Inputs!E$10+IF(ISNUMBER(Scorecard!N14),Scorecard!N14,Inputs!$B$4)*Inputs!F$10)/Inputs!$G$10 -> 42.573153 | D13: =(IF(ISNUMBER(Scorecard!J14),Scorecard!J14,Inputs!$B$4)*Inputs!B$11+IF(ISNUMBER(Scorecard!K14),Scorecard!K14,Inputs!$B$4)*Inputs!C$11+IF(ISNUMBER(Scorecard!L14),Scorecard!L14,Inputs!$B$4)*Inputs!D$11+IF(ISNUMBER(Scorecard!M14),Scorecard!M14,Inputs!$B$4)*Inputs!E$11+IF(ISNUMBER(Scorecard!N14),Scorecard!N14,Inputs!$B$4)*Inputs!F$11)/Inputs!$G$11 -> 32.714884 | E13: =(IF(ISNUMBER(Scorecard!J14),Scorecard!J14,Inputs!$B$4)*Inputs!B$12+IF(ISNUMBER(Scorecard!K14),Scorecard!K14,Inputs!$B$4)*Inputs!C$12+IF(ISNUMBER(Scorecard!L14),Scorecard!L14,Inputs!$B$4)*Inputs!D$12+IF(ISNUMBER(Scorecard!M14),Scorecard!M14,Inputs!$B$4)*Inputs!E$12+IF(ISNUMBER(Scorecard!N14),Scorecard!N14,Inputs!$B$4)*Inputs!F$12)/Inputs!$G$12 -> 55.822503 | F13: =(IF(ISNUMBER(Scorecard!J14),Scorecard!J14,Inputs!$B$4)*Inputs!B$13+IF(ISNUMBER(Scorecard!K14),Scorecard!K14,Inputs!$B$4)*Inputs!C$13+IF(ISNUMBER(Scorecard!L14),Scorecard!L14,Inputs!$B$4)*Inputs!D$13+IF(ISNUMBER(Scorecard!M14),Scorecard!M14,Inputs!$B$4)*Inputs!E$13+IF(ISNUMBER(Scorecard!N14),Scorecard!N14,Inputs!$B$4)*Inputs!F$13)/Inputs!$G$13 -> 39.573592 | G13: =RANK(B13,B$5:B$14) -> 6 | H13: =RANK(C13,C$5:C$14) -> 6 | I13: =RANK(D13,D$5:D$14) -> 7 | J13: =RANK(E13,E$5:E$14) -> 5 | K13: =RANK(F13,F$5:F$14) -> 6 | L13: =MIN(G13:K13) -> 5 | M13: =MAX(G13:K13) -> 7 | N13: =IF(M13-L13<=3,"Stable","Sensitive") -> Stable
A14: =Scorecard!A15 -> Manufacturing | B14: =(IF(ISNUMBER(Scorecard!J15),Scorecard!J15,Inputs!$B$4)*Inputs!B$9+IF(ISNUMBER(Scorecard!K15),Scorecard!K15,Inputs!$B$4)*Inputs!C$9+IF(ISNUMBER(Scorecard!L15),Scorecard!L15,Inputs!$B$4)*Inputs!D$9+IF(ISNUMBER(Scorecard!M15),Scorecard!M15,Inputs!$B$4)*Inputs!E$9+IF(ISNUMBER(Scorecard!N15),Scorecard!N15,Inputs!$B$4)*Inputs!F$9)/Inputs!$G$9 -> 30.477508 | C14: =(IF(ISNUMBER(Scorecard!J15),Scorecard!J15,Inputs!$B$4)*Inputs!B$10+IF(ISNUMBER(Scorecard!K15),Scorecard!K15,Inputs!$B$4)*Inputs!C$10+IF(ISNUMBER(Scorecard!L15),Scorecard!L15,Inputs!$B$4)*Inputs!D$10+IF(ISNUMBER(Scorecard!M15),Scorecard!M15,Inputs!$B$4)*Inputs!E$10+IF(ISNUMBER(Scorecard!N15),Scorecard!N15,Inputs!$B$4)*Inputs!F$10)/Inputs!$G$10 -> 26.973511 | D14: =(IF(ISNUMBER(Scorecard!J15),Scorecard!J15,Inputs!$B$4)*Inputs!B$11+IF(ISNUMBER(Scorecard!K15),Scorecard!K15,Inputs!$B$4)*Inputs!C$11+IF(ISNUMBER(Scorecard!L15),Scorecard!L15,Inputs!$B$4)*Inputs!D$11+IF(ISNUMBER(Scorecard!M15),Scorecard!M15,Inputs!$B$4)*Inputs!E$11+IF(ISNUMBER(Scorecard!N15),Scorecard!N15,Inputs!$B$4)*Inputs!F$11)/Inputs!$G$11 -> 30.470157 | E14: =(IF(ISNUMBER(Scorecard!J15),Scorecard!J15,Inputs!$B$4)*Inputs!B$12+IF(ISNUMBER(Scorecard!K15),Scorecard!K15,Inputs!$B$4)*Inputs!C$12+IF(ISNUMBER(Scorecard!L15),Scorecard!L15,Inputs!$B$4)*Inputs!D$12+IF(ISNUMBER(Scorecard!M15),Scorecard!M15,Inputs!$B$4)*Inputs!E$12+IF(ISNUMBER(Scorecard!N15),Scorecard!N15,Inputs!$B$4)*Inputs!F$12)/Inputs!$G$12 -> 33.159628 | F14: =(IF(ISNUMBER(Scorecard!J15),Scorecard!J15,Inputs!$B$4)*Inputs!B$13+IF(ISNUMBER(Scorecard!K15),Scorecard!K15,Inputs!$B$4)*Inputs!C$13+IF(ISNUMBER(Scorecard!L15),Scorecard!L15,Inputs!$B$4)*Inputs!D$13+IF(ISNUMBER(Scorecard!M15),Scorecard!M15,Inputs!$B$4)*Inputs!E$13+IF(ISNUMBER(Scorecard!N15),Scorecard!N15,Inputs!$B$4)*Inputs!F$13)/Inputs!$G$13 -> 28.952254 | G14: =RANK(B14,B$5:B$14) -> 9 | H14: =RANK(C14,C$5:C$14) -> 9 | I14: =RANK(D14,D$5:D$14) -> 9 | J14: =RANK(E14,E$5:E$14) -> 6 | K14: =RANK(F14,F$5:F$14) -> 9 | L14: =MIN(G14:K14) -> 6 | M14: =MAX(G14:K14) -> 9 | N14: =IF(M14-L14<=3,"Stable","Sensitive") -> Stable

Sheet Inputs
A1: Inputs and scenario weights
A2: Weights are % of the total score. Pick the scenario used on the Scorecard.
A3: Selected scenario | B3: Balanced
A4: Neutral score for missing credit pillar | B4: 50
A5: Tier cut-off: Lead = rank at or below | B5: 3
A6: Tier cut-off: Grow = rank at or below | B6: 7
A8: Scenario | B8: Scale | C8: Recent growth | D8: Track record | E8: Credit demand | F8: Credit health | G8: Total
A9: Balanced | B9: 20 | C9: 25 | D9: 15 | E9: 20 | F9: 20 | G9: =SUM(B9:F9) -> 100
A10: Growth-led | B10: 10 | C10: 35 | D10: 25 | E10: 20 | F10: 10 | G10: =SUM(B10:F10) -> 100
A11: Risk-aware | B11: 20 | C11: 15 | D11: 10 | E11: 15 | F11: 40 | G11: =SUM(B11:F11) -> 100
A12: Scale-led | B12: 45 | C12: 15 | D12: 10 | E12: 15 | F12: 15 | G12: =SUM(B12:F12) -> 100
A13: Equal | B13: 20 | C13: 20 | D13: 20 | E13: 20 | F13: 20 | G13: =SUM(B13:F13) -> 100

Sheet GDP
A1: KNBS real GDP by activity (constant 2016 prices, KSh million)
A2: Source: KNBS Quarterly Gross Domestic Product Report, First Quarter 2026, Table 2. Column B is the editable group mapping.
A4: Activity | B4: Industry group | C4: FY2021 | D4: FY2024 | E4: FY2025 | F4: Q1 2025 | G4: Q1 2026 | H4: Growth 2025 % | I4: Growth Q1 2026 %
A5: Agriculture | B5: Agribusiness | C5: 1699959 | D5: 1862520 | E5: 1920338 | F5: 541319 | G5: 568027 | H5: =E5/D5*100-100 -> 3.1042888 | I5: =G5/F5*100-100 -> 4.9338745
A6: Mining & Quarrying | B6: Energy & Resources | C6: 103842 | D6: 97768 | E6: 112338 | F6: 25628 | G6: 27954 | H6: =E6/D6*100-100 -> 14.902627 | I6: =G6/F6*100-100 -> 9.0760106
A7: Manufacturing | B7: Manufacturing | C7: 810827 | D7: 874876 | E7: 892166 | F7: 221136 | G7: 230901 | H7: =E7/D7*100-100 -> 1.9762801 | I7: =G7/F7*100-100 -> 4.4158346
A8: Electricity & Water Supply | B8: Energy & Resources | C8: 231759 | D8: 259182 | E8: 272702 | F8: 65715 | G8: 68571 | H8: =E8/D8*100-100 -> 5.2164116 | I8: =G8/F8*100-100 -> 4.3460397
A9: Construction | B9: Real Estate & Construction | C9: 552764 | D9: 588156 | E9: 628320 | F9: 150281 | G9: 160133 | H9: =E9/D9*100-100 -> 6.8288005 | I9: =G9/F9*100-100 -> 6.555719
A10: Wholesale & Retail Trade | B10: Consumer & Retail | C10: 786202 | D10: 874817 | E10: 905941 | F10: 239942 | G10: 249638 | H10: =E10/D10*100-100 -> 3.5577727 | I10: =G10/F10*100-100 -> 4.0409766
A11: Accommodation & Food Services | B11: Consumer & Retail | C11: 81037 | D11: 172785 | E11: 199664 | F11: 47352 | G11: 54331 | H11: =E11/D11*100-100 -> 15.556327 | I11: =G11/F11*100-100 -> 14.738554
A12: Transportation & Storage | B12: Transport & Logistics | C12: 891983 | D12: 1038796 | E12: 1077187 | F12: 255011 | G12: 264187 | H12: =E12/D12*100-100 -> 3.6957208 | I12: =G12/F12*100-100 -> 3.5982762
A13: Information & Communication | B13: Technology, Media & Telecom | C13: 290224 | D13: 373860 | E13: 391886 | F13: 96655 | G13: 101463 | H13: =E13/D13*100-100 -> 4.821591 | I13: =G13/F13*100-100 -> 4.9743935
A14: Financial & Insurance | B14: Financial Services | C14: 802964 | D14: 1065163 | E14: 1134626 | F14: 257934 | G14: 274128 | H14: =E14/D14*100-100 -> 6.5213493 | I14: =G14/F14*100-100 -> 6.2783503
A15: Public Administration | B15: Public Sector & Development | C15: 564957 | D15: 677991 | E15: 734372 | F15: 174665 | G15: 184616 | H15: =E15/D15*100-100 -> 8.3158921 | I15: =G15/F15*100-100 -> 5.6971918
A16: Professional, Admin & Support Services | B16: Excluded | C16: 244148 | D16: 312376 | E16: 328078 | F16: 79636 | G16: 81559 | H16: =E16/D16*100-100 -> 5.0266346 | I16: =G16/F16*100-100 -> 2.4147371
... A21: FISIM | B21: Excluded | C21: -287975 | D21: -325317 | E21: -325971 | F21: -80173 | G21: -76917 | H21: =E21/D21*100-100 -> 0.20103468 | I21: =G21/F21*100-100 -> -4.0612176
A22: All industries at basic prices (published) | C22: 8597270 | D22: 9993801 | E22: 10470414 | F22: 2613759 | G22: 2753654
A23: Sum of activities listed (excludes FISIM adjustment) | C23: =SUM(C5:C21) -> 8597271 | D23: =SUM(D5:D21) -> 9993801 | E23: =SUM(E5:E21) -> 10470413 | F23: =SUM(F5:F21) -> 2613758 | G23: =SUM(G5:G21) -> 2753654
A24: Difference vs published (FISIM) | C24: =C22-C23 -> -1 | D24: =D22-D23 -> 0 | E24: =E22-E23 -> 1 | F24: =F22-F23 -> 1 | G24: =G22-G23 -> 0

Sheet Credit_Raw
A1: CBK bank lending, NPLs and credit officer survey by sector
A2: Sources: CBK Bank Supervision Annual Report 2025, Table 18 (Dec 2025); CBK Credit Officer Survey, quarter ended June 2026 (% of respondents).
A4: Bank sector | B4: Loan accounts | C4: Gross loans KSh m | D4: Gross NPLs KSh m | E4: NPL ratio % | F4: Demand: increased % | G4: Demand: unchanged % | H4: Demand: decreased % | I4: Standards: tightened % | J4: Standards: eased % | K4: NPL outlook: increase % | L4: NPL outlook: decrease %
A5: Trade | B5: 610882 | C5: 857832.3 | D5: 170564.2 | E5: =D5/C5*100 -> 19.883164 | F5: 65 | G5: 30 | H5: 5 | I5: 16 | J5: 29 | K5: 29 | L5: 39
A6: Real Estate | B6: 30459 | C6: 511116.3 | D6: 113797.5 | E6: =D6/C6*100 -> 22.264502 | F6: 28 | G6: 44 | H6: 28 | I6: 30 | J6: 8 | K6: 27 | L6: 27
A7: Manufacturing | B7: 34456 | C7: 584989.3 | D7: 107629.6 | E7: =D7/C7*100 -> 18.398559 | F7: 41 | G7: 49 | H7: 11 | I7: 13 | J7: 21 | K7: 21 | L7: 34
A8: Personal and Household | B8: 14849679 | C8: 1176958.3 | D8: 114045.7 | E8: =D8/C8*100 -> 9.6898675 | F8: 66 | G8: 29 | H8: 6 | I8: 27 | J8: 24 | K8: 35 | L8: 43
A9: Building and Construction | B9: 17904 | C9: 175519.6 | D9: 51767.8 | E9: =D9/C9*100 -> 29.494028 | F9: 42 | G9: 53 | H9: 6 | I9: 16 | J9: 11 | K9: 24 | L9: 41
A10: Transport and Communication | B10: 53357 | C10: 321105.5 | D10: 53180.9 | E10: =D10/C10*100 -> 16.561815 | F10: 32 | G10: 43 | H10: 24 | I10: 18 | J10: 11 | K10: 18 | L10: 37
A11: Agriculture | B11: 127031 | C11: 197895.5 | D11: 38134.6 | E11: =D11/C11*100 -> 19.270069 | F11: 35 | G11: 49 | H11: 16 | I11: 13 | J11: 18 | K11: 16 | L11: 29
A12: Tourism, Restaurant and Hotels | B12: 10902 | C12: 99113.8 | D12: 22657.2 | E12: =D12/C12*100 -> 22.859783 | F12: 19 | G12: 56 | H12: 25 | I12: 19 | J12: 8 | K12: 24 | L12: 35
A13: Energy and Water | B13: 5028 | C13: 142807.6 | D13: 9777.9 | E13: =D13/C13*100 -> 6.8469045 | F13: 38 | G13: 54 | H13: 8 | I13: 11 | J13: 11 | K13: 19 | L13: 22
A14: Financial Services | B14: 18277 | C14: 241698.4 | D14: 7864.2 | E14: =D14/C14*100 -> 3.2537245 | F14: 38 | G14: 46 | H14: 16 | I14: 11 | J14: 11 | K14: 13 | L14: 34
A15: Mining and Quarrying | B15: 1133 | C15: 38127.5 | D15: 7511.5 | E15: =D15/C15*100 -> 19.701003 | F15: 14 | G15: 84 | H15: 3 | I15: 13 | J15: 5 | K15: 11 | L15: 26
A16: Total | B16: =SUM(B5:B15) -> 15759108 | C16: =SUM(C5:C15) -> 4347164.1 | D16: =SUM(D5:D15) -> 696931.1 | E16: =D16/C16*100 -> 16.031856

Sheet Credit_Map
A1: Mapping of industry groups to CBK bank sectors
A2: Editable (blue). Transport and Communication is shared by two groups.
A4: Industry group | B4: Bank sector | C4: Gross loans | D4: Gross NPLs | E4: Demand up % | F4: Demand down %
A5: Financial Services | B5: Financial Services | C5: =INDEX(Credit_Raw!$C$5:$C$15,MATCH($B5,Credit_Raw!$A$5:$A$15,0)) -> 241698.4 | D5: =INDEX(Credit_Raw!$D$5:$D$15,MATCH($B5,Credit_Raw!$A$5:$A$15,0)) -> 7864.2 | E5: =INDEX(Credit_Raw!$F$5:$F$15,MATCH($B5,Credit_Raw!$A$5:$A$15,0)) -> 38 | F5: =INDEX(Credit_Raw!$H$5:$H$15,MATCH($B5,Credit_Raw!$A$5:$A$15,0)) -> 16
A6: Energy & Resources | B6: Energy and Water | C6: =INDEX(Credit_Raw!$C$5:$C$15,MATCH($B6,Credit_Raw!$A$5:$A$15,0)) -> 142807.6 | D6: =INDEX(Credit_Raw!$D$5:$D$15,MATCH($B6,Credit_Raw!$A$5:$A$15,0)) -> 9777.9 | E6: =INDEX(Credit_Raw!$F$5:$F$15,MATCH($B6,Credit_Raw!$A$5:$A$15,0)) -> 38 | F6: =INDEX(Credit_Raw!$H$5:$H$15,MATCH($B6,Credit_Raw!$A$5:$A$15,0)) -> 8
A7: Energy & Resources | B7: Mining and Quarrying | C7: =INDEX(Credit_Raw!$C$5:$C$15,MATCH($B7,Credit_Raw!$A$5:$A$15,0)) -> 38127.5 | D7: =INDEX(Credit_Raw!$D$5:$D$15,MATCH($B7,Credit_Raw!$A$5:$A$15,0)) -> 7511.5 | E7: =INDEX(Credit_Raw!$F$5:$F$15,MATCH($B7,Credit_Raw!$A$5:$A$15,0)) -> 14 | F7: =INDEX(Credit_Raw!$H$5:$H$15,MATCH($B7,Credit_Raw!$A$5:$A$15,0)) -> 3
A8: Technology, Media & Telecom | B8: Transport and Communication | C8: =INDEX(Credit_Raw!$C$5:$C$15,MATCH($B8,Credit_Raw!$A$5:$A$15,0)) -> 321105.5 | D8: =INDEX(Credit_Raw!$D$5:$D$15,MATCH($B8,Credit_Raw!$A$5:$A$15,0)) -> 53180.9 | E8: =INDEX(Credit_Raw!$F$5:$F$15,MATCH($B8,Credit_Raw!$A$5:$A$15,0)) -> 32 | F8: =INDEX(Credit_Raw!$H$5:$H$15,MATCH($B8,Credit_Raw!$A$5:$A$15,0)) -> 24
A9: Transport & Logistics | B9: Transport and Communication | C9: =INDEX(Credit_Raw!$C$5:$C$15,MATCH($B9,Credit_Raw!$A$5:$A$15,0)) -> 321105.5 | D9: =INDEX(Credit_Raw!$D$5:$D$15,MATCH($B9,Credit_Raw!$A$5:$A$15,0)) -> 53180.9 | E9: =INDEX(Credit_Raw!$F$5:$F$15,MATCH($B9,Credit_Raw!$A$5:$A$15,0)) -> 32 | F9: =INDEX(Credit_Raw!$H$5:$H$15,MATCH($B9,Credit_Raw!$A$5:$A$15,0)) -> 24
A10: Consumer & Retail | B10: Trade | C10: =INDEX(Credit_Raw!$C$5:$C$15,MATCH($B10,Credit_Raw!$A$5:$A$15,0)) -> 857832.3 | D10: =INDEX(Credit_Raw!$D$5:$D$15,MATCH($B10,Credit_Raw!$A$5:$A$15,0)) -> 170564.2 | E10: =INDEX(Credit_Raw!$F$5:$F$15,MATCH($B10,Credit_Raw!$A$5:$A$15,0)) -> 65 | F10: =INDEX(Credit_Raw!$H$5:$H$15,MATCH($B10,Credit_Raw!$A$5:$A$15,0)) -> 5
A11: Consumer & Retail | B11: Tourism, Restaurant and Hotels | C11: =INDEX(Credit_Raw!$C$5:$C$15,MATCH($B11,Credit_Raw!$A$5:$A$15,0)) -> 99113.8 | D11: =INDEX(Credit_Raw!$D$5:$D$15,MATCH($B11,Credit_Raw!$A$5:$A$15,0)) -> 22657.2 | E11: =INDEX(Credit_Raw!$F$5:$F$15,MATCH($B11,Credit_Raw!$A$5:$A$15,0)) -> 19 | F11: =INDEX(Credit_Raw!$H$5:$H$15,MATCH($B11,Credit_Raw!$A$5:$A$15,0)) -> 25
A12: Agribusiness | B12: Agriculture | C12: =INDEX(Credit_Raw!$C$5:$C$15,MATCH($B12,Credit_Raw!$A$5:$A$15,0)) -> 197895.5 | D12: =INDEX(Credit_Raw!$D$5:$D$15,MATCH($B12,Credit_Raw!$A$5:$A$15,0)) -> 38134.6 | E12: =INDEX(Credit_Raw!$F$5:$F$15,MATCH($B12,Credit_Raw!$A$5:$A$15,0)) -> 35 | F12: =INDEX(Credit_Raw!$H$5:$H$15,MATCH($B12,Credit_Raw!$A$5:$A$15,0)) -> 16
A13: Real Estate & Construction | B13: Real Estate | C13: =INDEX(Credit_Raw!$C$5:$C$15,MATCH($B13,Credit_Raw!$A$5:$A$15,0)) -> 511116.3 | D13: =INDEX(Credit_Raw!$D$5:$D$15,MATCH($B13,Credit_Raw!$A$5:$A$15,0)) -> 113797.5 | E13: =INDEX(Credit_Raw!$F$5:$F$15,MATCH($B13,Credit_Raw!$A$5:$A$15,0)) -> 28 | F13: =INDEX(Credit_Raw!$H$5:$H$15,MATCH($B13,Credit_Raw!$A$5:$A$15,0)) -> 28
A14: Real Estate & Construction | B14: Building and Construction | C14: =INDEX(Credit_Raw!$C$5:$C$15,MATCH($B14,Credit_Raw!$A$5:$A$15,0)) -> 175519.6 | D14: =INDEX(Credit_Raw!$D$5:$D$15,MATCH($B14,Credit_Raw!$A$5:$A$15,0)) -> 51767.8 | E14: =INDEX(Credit_Raw!$F$5:$F$15,MATCH($B14,Credit_Raw!$A$5:$A$15,0)) -> 42 | F14: =INDEX(Credit_Raw!$H$5:$H$15,MATCH($B14,Credit_Raw!$A$5:$A$15,0)) -> 6
A15: Manufacturing | B15: Manufacturing | C15: =INDEX(Credit_Raw!$C$5:$C$15,MATCH($B15,Credit_Raw!$A$5:$A$15,0)) -> 584989.3 | D15: =INDEX(Credit_Raw!$D$5:$D$15,MATCH($B15,Credit_Raw!$A$5:$A$15,0)) -> 107629.6 | E15: =INDEX(Credit_Raw!$F$5:$F$15,MATCH($B15,Credit_Raw!$A$5:$A$15,0)) -> 41 | F15: =INDEX(Credit_Raw!$H$5:$H$15,MATCH($B15,Credit_Raw!$A$5:$A$15,0)) -> 11

Sheet Signals
A1: Real-economy signals, 2021-2025
A2: Source: KNBS Economic Survey 2026, Annex 1 Table 0 (2025 provisional).
A4: Indicator | B4: Unit | C4: 2021 | D4: 2022 | E4: 2023 | F4: 2024 | G4: 2025 | H4: Growth 2025 % | I4: CAGR 2021-25 %
A5: GDP (Current) at Market Prices | B5: KSh Mn | C5: 12027662 | D5: 13489642 | E5: 15033610 | F5: 16232295 | G5: 17577557 | H5: =G5/F5*100-100 -> 8.2875676 | I5: =((G5/C5)^(1/4)-1)*100 -> 9.9497714
A6: Money Supply (M3) | B6: KSh Mn | C6: 4689439 | D6: 5042419 | E6: 6044533 | F6: 6048537 | G6: 6731191 | H6: =G6/F6*100-100 -> 11.286266 | I6: =((G6/C6)^(1/4)-1)*100 -> 9.4568021
A7: Total domestic credit | B7: KSh Mn | C7: 5566513 | D7: 6246348 | E7: 7041087 | F7: 7140299 | G7: 7862296 | H7: =G7/F7*100-100 -> 10.111579 | I7: =((G7/C7)^(1/4)-1)*100 -> 9.0163257
A8: Tea-marketed production | B8: '000 tonnes | C8: 537.8 | D8: 535 | E8: 570.3 | F8: 598.5 | G8: 550.4 | H8: =G8/F8*100-100 -> -8.0367586 | I8: =((G8/C8)^(1/4)-1)*100 -> 0.5806428
A9: Fresh Horticultural Produce exports | B9: '000 tonnes | C9: 405.5 | D9: 391.5 | E9: 468.4 | F9: 402.2 | G9: 457.9 | H9: =G9/F9*100-100 -> 13.848831 | I9: =((G9/C9)^(1/4)-1)*100 -> 3.0848744
A10: Milk sold centrally | B10: Mn litres | C10: 801.9 | D10: 755.3 | E10: 810.8 | F10: 909 | G10: 1013.7 | H10: =G10/F10*100-100 -> 11.518152 | I10: =((G10/C10)^(1/4)-1)*100 -> 6.0345282
A11: Manufacturing output | B11: KSh Mn | C11: 2700161.2 | D11: 3168615 | E11: 3511497.7 | F11: 3689334.1 | G11: 3817390.6 | H11: =G11/F11*100-100 -> 3.4709922 | I11: =((G11/C11)^(1/4)-1)*100 -> 9.042105
A12: Construction output | B12: KSh Mn | C12: 1821644 | D12: 2042781.5 | E12: 2119786.8 | F12: 2171266 | G12: 2374337.8 | H12: =G12/F12*100-100 -> 9.352691 | I12: =((G12/C12)^(1/4)-1)*100 -> 6.8488248
A13: Cement Consumption | B13: '000 tonnes | C13: 9098.4 | D13: 9456.8 | E13: 9195.8 | F13: 8542.7 | G13: 10280.2 | H13: =G13/F13*100-100 -> 20.339003 | I13: =((G13/C13)^(1/4)-1)*100 -> 3.1001114
A14: Electricity consumption | B14: GWh | C14: 9565.4 | D14: 10008.4 | E14: 10320.6 | F14: 10751.7 | G14: 11785.5 | H14: =G14/F14*100-100 -> 9.6152236 | I14: =((G14/C14)^(1/4)-1)*100 -> 5.356472
A15: Rail freight | B15: '000 tonnes | C15: 6051 | D15: 6877 | E15: 7534 | F15: 7560 | G15: 8415 | H15: =G15/F15*100-100 -> 11.309524 | I15: =((G15/C15)^(1/4)-1)*100 -> 8.5942279
A16: Air passengers handled | B16: '000 No. | C16: 6703.5 | D16: 10238.6 | E16: 12205.8 | F16: 12831.8 | G16: 12676.6 | H16: =G16/F16*100-100 -> -1.2094952 | I16: =((G16/C16)^(1/4)-1)*100 -> 17.266859
... A23: Total National Government Expenditure | B23: KSh Mn | C23: 3027518 | D23: 3218186.9 | E23: 3605209.1 | F23: 4077992.4 | G23: 4269579.8 | H23: =G23/F23*100-100 -> 4.6980813 | I23: =((G23/C23)^(1/4)-1)*100 -> 8.9744285

Sheet Python_Ref
A1: Independent Python results (analysis/model.py)
A3: group | B3: value_added_2025_ksh_m | C3: share_of_gdp_pct | D3: growth_2025_pct | E3: cagr_2021_25_pct | F3: growth_q1_2026_pct | G3: gross_loans_ksh_m | H3: npl_ratio_pct | I3: credit_demand_net_pct | J3: score_Balanced | K3: score_Growth-led | L3: score_Risk-aware | M3: score_Scale-led | N3: score_Equal | O3: rank_Balanced | P3: rank_Growth-led | Q3: rank_Risk-aware | R3: rank_Scale-led | S3: rank_Equal
A4: Financial Services | B4: 1134626 | C4: 10.836496 | D4: 6.5213493 | E4: 9.0282808 | F4: 6.2783503 | G4: 241698.4 | H4: 3.2537245 | I4: 22 | J4: 76.746877 | K4: 81.47324 | L4: 80.196976 | M4: 68.381069 | N4: 76.746877 | O4: 1 | P4: 1 | Q4: 1 | R4: 1 | S4: 1
A5: Energy & Resources | B5: 385040 | C5: 3.6774095 | D5: 7.8694495 | E5: 3.4953054 | F5: 5.6731222 | G5: 180935.1 | H5: 9.555581 | I5: 25.99623 | J5: 45.253634 | K5: 46.880818 | L5: 48.662768 | M5: 33.127225 | N5: 42.197172 | O5: 4 | P5: 4 | Q5: 4 | R5: 7 | S5: 4
A6: Technology, Media & Telecom | B6: 391886 | C6: 3.7427937 | D6: 4.821591 | E6: 7.7969831 | F6: 4.9743935 | G6: 321105.5 | H6: 16.561815 | I6: 8 | J6: 33.893572 | K6: 42.739605 | L6: 31.930236 | M6: 24.89486 | N6: 35.394807 | O6: 7 | P6: 5 | Q6: 8 | R6: 9 | S6: 7
A7: Transport & Logistics | B7: 1077187 | C7: 10.287912 | D7: 3.6957208 | E7: 4.8295283 | F7: 3.5982762 | G7: 321105.5 | H7: 16.561815 | I7: 8 | J7: 22.56725 | K7: 17.666664 | L7: 27.98336 | M7: 31.253863 | N7: 24.390975 | O7: 10 | P7: 10 | Q7: 10 | R7: 8 | S7: 10
A8: Public Sector & Development | B8: 1273606 | C8: 12.163855 | D8: 5.9295658 | E8: 5.5228987 | F8: 5.9081245 | J8: 60.810548 | K8: 63.015984 | L8: 57.343703 | M8: 60.117842 | N8: 58.849495 | O8: 3 | P8: 3 | Q8: 2 | R8: 3 | S8: 3
A9: Health | B9: 257935 | C9: 2.4634652 | D9: 5.5250992 | E9: 4.8367026 | F9: 4.3111255 | J9: 32.136989 | K9: 33.455106 | L9: 35.148024 | M9: 22.648024 | N9: 32.636235 | O9: 8 | P9: 8 | Q9: 6 | R9: 10 | S9: 8
A10: Consumer & Retail | B10: 1105605 | C10: 10.559325 | D10: 5.5367401 | E10: 6.2588958 | F10: 5.8041588 | G10: 956946.1 | H10: 20.191461 | I10: 53.164181 | J10: 63.249496 | K10: 70.311323 | L10: 50.873435 | M10: 58.921558 | N10: 62.039172 | O10: 2 | P10: 2 | Q10: 3 | R10: 4 | S10: 2
A11: Agribusiness | B11: 1920338 | C11: 18.340612 | D11: 3.1042888 | E11: 3.0943363 | F11: 4.9338745 | G11: 197895.5 | H11: 19.270069 | I11: 19 | J11: 43.506058 | K11: 37.190126 | L11: 41.436841 | M11: 60.632983 | N11: 41.525426 | O11: 5 | P11: 7 | Q11: 5 | R11: 2 | S11: 5
A12: Real Estate & Construction | B12: 1794502 | C12: 17.138787 | D12: 4.8998615 | E12: 4.5163781 | F12: 5.5021607 | G12: 686635.9 | H12: 24.112532 | I12: 9.2024108 | J12: 41.538684 | K12: 42.573153 | L12: 32.714884 | M12: 55.822503 | N12: 39.573592 | O12: 6 | P12: 6 | Q12: 7 | R12: 5 | S12: 6
A13: Manufacturing | B13: 892166 | C13: 8.5208283 | D13: 1.9762801 | E13: 2.4187254 | F13: 4.4158346 | G13: 584989.3 | H13: 18.398559 | I13: 30 | J13: 30.477508 | K13: 26.973511 | L13: 30.470157 | M13: 33.159628 | N13: 28.952254 | O13: 9 | P13: 9 | Q13: 9 | R13: 6 | S13: 9

Sheet Checks
A1: Reconciliation: workbook formulas vs Python
A2: Absolute tolerance 0.001 (levels 0.5).
A3: Check | B3: Workbook | C3: Python | D3: Abs diff | E3: Result
A4: Financial Services: value added | B4: =Scorecard!B6 -> 1134626 | C4: =Python_Ref!B4 -> 1134626 | D4: =ABS(B4-C4) -> 0 | E4: =IF(D4<=0.5,"PASS","FAIL") -> PASS
A5: Financial Services: growth 2025 | B5: =Scorecard!D6 -> 6.5213493 | C5: =Python_Ref!D4 -> 6.5213493 | D5: =ABS(B5-C5) -> 0 | E5: =IF(D5<=0.001,"PASS","FAIL") -> PASS
A6: Financial Services: CAGR | B6: =Scorecard!E6 -> 9.0282808 | C6: =Python_Ref!E4 -> 9.0282808 | D6: =ABS(B6-C6) -> 0 | E6: =IF(D6<=0.001,"PASS","FAIL") -> PASS
A7: Financial Services: Q1 2026 growth | B7: =Scorecard!F6 -> 6.2783503 | C7: =Python_Ref!F4 -> 6.2783503 | D7: =ABS(B7-C7) -> 0 | E7: =IF(D7<=0.001,"PASS","FAIL") -> PASS
A8: Financial Services: NPL ratio | B8: =Scorecard!H6 -> 3.2537245 | C8: =Python_Ref!H4 -> 3.2537245 | D8: =ABS(B8-C8) -> 0 | E8: =IF(D8<=0.001,"PASS","FAIL") -> PASS
A9: Financial Services: credit demand net | B9: =Scorecard!I6 -> 22 | C9: =Python_Ref!I4 -> 22 | D9: =ABS(B9-C9) -> 0 | E9: =IF(D9<=0.001,"PASS","FAIL") -> PASS
A10: Financial Services: score Balanced | B10: =Scenarios!B5 -> 76.746877 | C10: =Python_Ref!J4 -> 76.746877 | D10: =ABS(B10-C10) -> 0 | E10: =IF(D10<=0.01,"PASS","FAIL") -> PASS
A11: Financial Services: rank Balanced | B11: =Scenarios!G5 -> 1 | C11: =Python_Ref!O4 -> 1 | D11: =ABS(B11-C11) -> 0 | E11: =IF(D11<=0,"PASS","FAIL") -> PASS
A12: Financial Services: score Growth-led | B12: =Scenarios!C5 -> 81.47324 | C12: =Python_Ref!K4 -> 81.47324 | D12: =ABS(B12-C12) -> 0 | E12: =IF(D12<=0.01,"PASS","FAIL") -> PASS
A13: Financial Services: rank Growth-led | B13: =Scenarios!H5 -> 1 | C13: =Python_Ref!P4 -> 1 | D13: =ABS(B13-C13) -> 0 | E13: =IF(D13<=0,"PASS","FAIL") -> PASS
A14: Financial Services: score Risk-aware | B14: =Scenarios!D5 -> 80.196976 | C14: =Python_Ref!L4 -> 80.196976 | D14: =ABS(B14-C14) -> 0 | E14: =IF(D14<=0.01,"PASS","FAIL") -> PASS
A15: Financial Services: rank Risk-aware | B15: =Scenarios!I5 -> 1 | C15: =Python_Ref!Q4 -> 1 | D15: =ABS(B15-C15) -> 0 | E15: =IF(D15<=0,"PASS","FAIL") -> PASS
A16: Financial Services: score Scale-led | B16: =Scenarios!E5 -> 68.381069 | C16: =Python_Ref!M4 -> 68.381069 | D16: =ABS(B16-C16) -> 0 | E16: =IF(D16<=0.01,"PASS","FAIL") -> PASS
A17: Financial Services: rank Scale-led | B17: =Scenarios!J5 -> 1 | C17: =Python_Ref!R4 -> 1 | D17: =ABS(B17-C17) -> 0 | E17: =IF(D17<=0,"PASS","FAIL") -> PASS
A18: Financial Services: score Equal | B18: =Scenarios!F5 -> 76.746877 | C18: =Python_Ref!N4 -> 76.746877 | D18: =ABS(B18-C18) -> 0 | E18: =IF(D18<=0.01,"PASS","FAIL") -> PASS
A19: Financial Services: rank Equal | B19: =Scenarios!K5 -> 1 | C19: =Python_Ref!S4 -> 1 | D19: =ABS(B19-C19) -> 0 | E19: =IF(D19<=0,"PASS","FAIL") -> PASS
A20: Energy & Resources: value added | B20: =Scorecard!B7 -> 385040 | C20: =Python_Ref!B5 -> 385040 | D20: =ABS(B20-C20) -> 0 | E20: =IF(D20<=0.5,"PASS","FAIL") -> PASS
A21: Energy & Resources: growth 2025 | B21: =Scorecard!D7 -> 7.8694495 | C21: =Python_Ref!D5 -> 7.8694495 | D21: =ABS(B21-C21) -> 0 | E21: =IF(D21<=0.001,"PASS","FAIL") -> PASS
A22: Energy & Resources: CAGR | B22: =Scorecard!E7 -> 3.4953054 | C22: =Python_Ref!E5 -> 3.4953054 | D22: =ABS(B22-C22) -> 0 | E22: =IF(D22<=0.001,"PASS","FAIL") -> PASS
A23: Energy & Resources: Q1 2026 growth | B23: =Scorecard!F7 -> 5.6731222 | C23: =Python_Ref!F5 -> 5.6731222 | D23: =ABS(B23-C23) -> 0 | E23: =IF(D23<=0.001,"PASS","FAIL") -> PASS
A24: Energy & Resources: NPL ratio | B24: =Scorecard!H7 -> 9.555581 | C24: =Python_Ref!H5 -> 9.555581 | D24: =ABS(B24-C24) -> 0 | E24: =IF(D24<=0.001,"PASS","FAIL") -> PASS
A25: Energy & Resources: credit demand net | B25: =Scorecard!I7 -> 25.99623 | C25: =Python_Ref!I5 -> 25.99623 | D25: =ABS(B25-C25) -> 0 | E25: =IF(D25<=0.001,"PASS","FAIL") -> PASS
A26: Energy & Resources: score Balanced | B26: =Scenarios!B6 -> 45.253634 | C26: =Python_Ref!J5 -> 45.253634 | D26: =ABS(B26-C26) -> 0 | E26: =IF(D26<=0.01,"PASS","FAIL") -> PASS
A27: Energy & Resources: rank Balanced | B27: =Scenarios!G6 -> 4 | C27: =Python_Ref!O5 -> 4 | D27: =ABS(B27-C27) -> 0 | E27: =IF(D27<=0,"PASS","FAIL") -> PASS
A28: Energy & Resources: score Growth-led | B28: =Scenarios!C6 -> 46.880818 | C28: =Python_Ref!K5 -> 46.880818 | D28: =ABS(B28-C28) -> 0 | E28: =IF(D28<=0.01,"PASS","FAIL") -> PASS
A29: Energy & Resources: rank Growth-led | B29: =Scenarios!H6 -> 4 | C29: =Python_Ref!P5 -> 4 | D29: =ABS(B29-C29) -> 0 | E29: =IF(D29<=0,"PASS","FAIL") -> PASS
A30: Energy & Resources: score Risk-aware | B30: =Scenarios!D6 -> 48.662768 | C30: =Python_Ref!L5 -> 48.662768 | D30: =ABS(B30-C30) -> 0 | E30: =IF(D30<=0.01,"PASS","FAIL") -> PASS
A31: Energy & Resources: rank Risk-aware | B31: =Scenarios!I6 -> 4 | C31: =Python_Ref!Q5 -> 4 | D31: =ABS(B31-C31) -> 0 | E31: =IF(D31<=0,"PASS","FAIL") -> PASS
A32: Energy & Resources: score Scale-led | B32: =Scenarios!E6 -> 33.127225 | C32: =Python_Ref!M5 -> 33.127225 | D32: =ABS(B32-C32) -> 0 | E32: =IF(D32<=0.01,"PASS","FAIL") -> PASS
A33: Energy & Resources: rank Scale-led | B33: =Scenarios!J6 -> 7 | C33: =Python_Ref!R5 -> 7 | D33: =ABS(B33-C33) -> 0 | E33: =IF(D33<=0,"PASS","FAIL") -> PASS
A34: Energy & Resources: score Equal | B34: =Scenarios!F6 -> 42.197172 | C34: =Python_Ref!N5 -> 42.197172 | D34: =ABS(B34-C34) -> 0 | E34: =IF(D34<=0.01,"PASS","FAIL") -> PASS
A35: Energy & Resources: rank Equal | B35: =Scenarios!K6 -> 4 | C35: =Python_Ref!S5 -> 4 | D35: =ABS(B35-C35) -> 0 | E35: =IF(D35<=0,"PASS","FAIL") -> PASS
A36: Technology, Media & Telecom: value added | B36: =Scorecard!B8 -> 391886 | C36: =Python_Ref!B6 -> 391886 | D36: =ABS(B36-C36) -> 0 | E36: =IF(D36<=0.5,"PASS","FAIL") -> PASS
A37: Technology, Media & Telecom: growth 2025 | B37: =Scorecard!D8 -> 4.821591 | C37: =Python_Ref!D6 -> 4.821591 | D37: =ABS(B37-C37) -> 0 | E37: =IF(D37<=0.001,"PASS","FAIL") -> PASS
A38: Technology, Media & Telecom: CAGR | B38: =Scorecard!E8 -> 7.7969831 | C38: =Python_Ref!E6 -> 7.7969831 | D38: =ABS(B38-C38) -> 0 | E38: =IF(D38<=0.001,"PASS","FAIL") -> PASS
A39: Technology, Media & Telecom: Q1 2026 growth | B39: =Scorecard!F8 -> 4.9743935 | C39: =Python_Ref!F6 -> 4.9743935 | D39: =ABS(B39-C39) -> 0 | E39: =IF(D39<=0.001,"PASS","FAIL") -> PASS
A40: Technology, Media & Telecom: NPL ratio | B40: =Scorecard!H8 -> 16.561815 | C40: =Python_Ref!H6 -> 16.561815 | D40: =ABS(B40-C40) -> 0 | E40: =IF(D40<=0.001,"PASS","FAIL") -> PASS
A41: Technology, Media & Telecom: credit demand net | B41: =Scorecard!I8 -> 8 | C41: =Python_Ref!I6 -> 8 | D41: =ABS(B41-C41) -> 0 | E41: =IF(D41<=0.001,"PASS","FAIL") -> PASS
A42: Technology, Media & Telecom: score Balanced | B42: =Scenarios!B7 -> 33.893572 | C42: =Python_Ref!J6 -> 33.893572 | D42: =ABS(B42-C42) -> 0 | E42: =IF(D42<=0.01,"PASS","FAIL") -> PASS
A43: Technology, Media & Telecom: rank Balanced | B43: =Scenarios!G7 -> 7 | C43: =Python_Ref!O6 -> 7 | D43: =ABS(B43-C43) -> 0 | E43: =IF(D43<=0,"PASS","FAIL") -> PASS
A44: Technology, Media & Telecom: score Growth-led | B44: =Scenarios!C7 -> 42.739605 | C44: =Python_Ref!K6 -> 42.739605 | D44: =ABS(B44-C44) -> 0 | E44: =IF(D44<=0.01,"PASS","FAIL") -> PASS
A45: Technology, Media & Telecom: rank Growth-led | B45: =Scenarios!H7 -> 5 | C45: =Python_Ref!P6 -> 5 | D45: =ABS(B45-C45) -> 0 | E45: =IF(D45<=0,"PASS","FAIL") -> PASS
A46: Technology, Media & Telecom: score Risk-aware | B46: =Scenarios!D7 -> 31.930236 | C46: =Python_Ref!L6 -> 31.930236 | D46: =ABS(B46-C46) -> 0 | E46: =IF(D46<=0.01,"PASS","FAIL") -> PASS
A47: Technology, Media & Telecom: rank Risk-aware | B47: =Scenarios!I7 -> 8 | C47: =Python_Ref!Q6 -> 8 | D47: =ABS(B47-C47) -> 0 | E47: =IF(D47<=0,"PASS","FAIL") -> PASS
A48: Technology, Media & Telecom: score Scale-led | B48: =Scenarios!E7 -> 24.89486 | C48: =Python_Ref!M6 -> 24.89486 | D48: =ABS(B48-C48) -> 0 | E48: =IF(D48<=0.01,"PASS","FAIL") -> PASS
A49: Technology, Media & Telecom: rank Scale-led | B49: =Scenarios!J7 -> 9 | C49: =Python_Ref!R6 -> 9 | D49: =ABS(B49-C49) -> 0 | E49: =IF(D49<=0,"PASS","FAIL") -> PASS
A50: Technology, Media & Telecom: score Equal | B50: =Scenarios!F7 -> 35.394807 | C50: =Python_Ref!N6 -> 35.394807 | D50: =ABS(B50-C50) -> 0 | E50: =IF(D50<=0.01,"PASS","FAIL") -> PASS
A51: Technology, Media & Telecom: rank Equal | B51: =Scenarios!K7 -> 7 | C51: =Python_Ref!S6 -> 7 | D51: =ABS(B51-C51) -> 0 | E51: =IF(D51<=0,"PASS","FAIL") -> PASS
A52: Transport & Logistics: value added | B52: =Scorecard!B9 -> 1077187 | C52: =Python_Ref!B7 -> 1077187 | D52: =ABS(B52-C52) -> 0 | E52: =IF(D52<=0.5,"PASS","FAIL") -> PASS
A53: Transport & Logistics: growth 2025 | B53: =Scorecard!D9 -> 3.6957208 | C53: =Python_Ref!D7 -> 3.6957208 | D53: =ABS(B53-C53) -> 0 | E53: =IF(D53<=0.001,"PASS","FAIL") -> PASS
A54: Transport & Logistics: CAGR | B54: =Scorecard!E9 -> 4.8295283 | C54: =Python_Ref!E7 -> 4.8295283 | D54: =ABS(B54-C54) -> 0 | E54: =IF(D54<=0.001,"PASS","FAIL") -> PASS
A55: Transport & Logistics: Q1 2026 growth | B55: =Scorecard!F9 -> 3.5982762 | C55: =Python_Ref!F7 -> 3.5982762 | D55: =ABS(B55-C55) -> 0 | E55: =IF(D55<=0.001,"PASS","FAIL") -> PASS
A56: Transport & Logistics: NPL ratio | B56: =Scorecard!H9 -> 16.561815 | C56: =Python_Ref!H7 -> 16.561815 | D56: =ABS(B56-C56) -> 0 | E56: =IF(D56<=0.001,"PASS","FAIL") -> PASS
A57: Transport & Logistics: credit demand net | B57: =Scorecard!I9 -> 8 | C57: =Python_Ref!I7 -> 8 | D57: =ABS(B57-C57) -> 0 | E57: =IF(D57<=0.001,"PASS","FAIL") -> PASS
A58: Transport & Logistics: score Balanced | B58: =Scenarios!B8 -> 22.56725 | C58: =Python_Ref!J7 -> 22.56725 | D58: =ABS(B58-C58) -> 0 | E58: =IF(D58<=0.01,"PASS","FAIL") -> PASS
A59: Transport & Logistics: rank Balanced | B59: =Scenarios!G8 -> 10 | C59: =Python_Ref!O7 -> 10 | D59: =ABS(B59-C59) -> 0 | E59: =IF(D59<=0,"PASS","FAIL") -> PASS
A60: Transport & Logistics: score Growth-led | B60: =Scenarios!C8 -> 17.666664 | C60: =Python_Ref!K7 -> 17.666664 | D60: =ABS(B60-C60) -> 0 | E60: =IF(D60<=0.01,"PASS","FAIL") -> PASS
A61: Transport & Logistics: rank Growth-led | B61: =Scenarios!H8 -> 10 | C61: =Python_Ref!P7 -> 10 | D61: =ABS(B61-C61) -> 0 | E61: =IF(D61<=0,"PASS","FAIL") -> PASS
A62: Transport & Logistics: score Risk-aware | B62: =Scenarios!D8 -> 27.98336 | C62: =Python_Ref!L7 -> 27.98336 | D62: =ABS(B62-C62) -> 0 | E62: =IF(D62<=0.01,"PASS","FAIL") -> PASS
A63: Transport & Logistics: rank Risk-aware | B63: =Scenarios!I8 -> 10 | C63: =Python_Ref!Q7 -> 10 | D63: =ABS(B63-C63) -> 0 | E63: =IF(D63<=0,"PASS","FAIL") -> PASS
A64: Transport & Logistics: score Scale-led | B64: =Scenarios!E8 -> 31.253863 | C64: =Python_Ref!M7 -> 31.253863 | D64: =ABS(B64-C64) -> 0 | E64: =IF(D64<=0.01,"PASS","FAIL") -> PASS
A65: Transport & Logistics: rank Scale-led | B65: =Scenarios!J8 -> 8 | C65: =Python_Ref!R7 -> 8 | D65: =ABS(B65-C65) -> 0 | E65: =IF(D65<=0,"PASS","FAIL") -> PASS
A66: Transport & Logistics: score Equal | B66: =Scenarios!F8 -> 24.390975 | C66: =Python_Ref!N7 -> 24.390975 | D66: =ABS(B66-C66) -> 0 | E66: =IF(D66<=0.01,"PASS","FAIL") -> PASS
A67: Transport & Logistics: rank Equal | B67: =Scenarios!K8 -> 10 | C67: =Python_Ref!S7 -> 10 | D67: =ABS(B67-C67) -> 0 | E67: =IF(D67<=0,"PASS","FAIL") -> PASS
A68: Public Sector & Development: value added | B68: =Scorecard!B10 -> 1273606 | C68: =Python_Ref!B8 -> 1273606 | D68: =ABS(B68-C68) -> 0 | E68: =IF(D68<=0.5,"PASS","FAIL") -> PASS
A69: Public Sector & Development: growth 2025 | B69: =Scorecard!D10 -> 5.9295658 | C69: =Python_Ref!D8 -> 5.9295658 | D69: =ABS(B69-C69) -> 0 | E69: =IF(D69<=0.001,"PASS","FAIL") -> PASS
A70: Public Sector & Development: CAGR | B70: =Scorecard!E10 -> 5.5228987 | C70: =Python_Ref!E8 -> 5.5228987 | D70: =ABS(B70-C70) -> 0 | E70: =IF(D70<=0.001,"PASS","FAIL") -> PASS
A71: Public Sector & Development: Q1 2026 growth | B71: =Scorecard!F10 -> 5.9081245 | C71: =Python_Ref!F8 -> 5.9081245 | D71: =ABS(B71-C71) -> 0 | E71: =IF(D71<=0.001,"PASS","FAIL") -> PASS
A72: Public Sector & Development: score Balanced | B72: =Scenarios!B9 -> 60.810548 | C72: =Python_Ref!J8 -> 60.810548 | D72: =ABS(B72-C72) -> 0 | E72: =IF(D72<=0.01,"PASS","FAIL") -> PASS
A73: Public Sector & Development: rank Balanced | B73: =Scenarios!G9 -> 3 | C73: =Python_Ref!O8 -> 3 | D73: =ABS(B73-C73) -> 0 | E73: =IF(D73<=0,"PASS","FAIL") -> PASS
A74: Public Sector & Development: score Growth-led | B74: =Scenarios!C9 -> 63.015984 | C74: =Python_Ref!K8 -> 63.015984 | D74: =ABS(B74-C74) -> 0 | E74: =IF(D74<=0.01,"PASS","FAIL") -> PASS
A75: Public Sector & Development: rank Growth-led | B75: =Scenarios!H9 -> 3 | C75: =Python_Ref!P8 -> 3 | D75: =ABS(B75-C75) -> 0 | E75: =IF(D75<=0,"PASS","FAIL") -> PASS
A76: Public Sector & Development: score Risk-aware | B76: =Scenarios!D9 -> 57.343703 | C76: =Python_Ref!L8 -> 57.343703 | D76: =ABS(B76-C76) -> 0 | E76: =IF(D76<=0.01,"PASS","FAIL") -> PASS
A77: Public Sector & Development: rank Risk-aware | B77: =Scenarios!I9 -> 2 | C77: =Python_Ref!Q8 -> 2 | D77: =ABS(B77-C77) -> 0 | E77: =IF(D77<=0,"PASS","FAIL") -> PASS
A78: Public Sector & Development: score Scale-led | B78: =Scenarios!E9 -> 60.117842 | C78: =Python_Ref!M8 -> 60.117842 | D78: =ABS(B78-C78) -> 0 | E78: =IF(D78<=0.01,"PASS","FAIL") -> PASS
A79: Public Sector & Development: rank Scale-led | B79: =Scenarios!J9 -> 3 | C79: =Python_Ref!R8 -> 3 | D79: =ABS(B79-C79) -> 0 | E79: =IF(D79<=0,"PASS","FAIL") -> PASS
A80: Public Sector & Development: score Equal | B80: =Scenarios!F9 -> 58.849495 | C80: =Python_Ref!N8 -> 58.849495 | D80: =ABS(B80-C80) -> 0 | E80: =IF(D80<=0.01,"PASS","FAIL") -> PASS
A81: Public Sector & Development: rank Equal | B81: =Scenarios!K9 -> 3 | C81: =Python_Ref!S8 -> 3 | D81: =ABS(B81-C81) -> 0 | E81: =IF(D81<=0,"PASS","FAIL") -> PASS
A82: Health: value added | B82: =Scorecard!B11 -> 257935 | C82: =Python_Ref!B9 -> 257935 | D82: =ABS(B82-C82) -> 0 | E82: =IF(D82<=0.5,"PASS","FAIL") -> PASS
A83: Health: growth 2025 | B83: =Scorecard!D11 -> 5.5250992 | C83: =Python_Ref!D9 -> 5.5250992 | D83: =ABS(B83-C83) -> 0 | E83: =IF(D83<=0.001,"PASS","FAIL") -> PASS
A84: Health: CAGR | B84: =Scorecard!E11 -> 4.8367026 | C84: =Python_Ref!E9 -> 4.8367026 | D84: =ABS(B84-C84) -> 0 | E84: =IF(D84<=0.001,"PASS","FAIL") -> PASS
A85: Health: Q1 2026 growth | B85: =Scorecard!F11 -> 4.3111255 | C85: =Python_Ref!F9 -> 4.3111255 | D85: =ABS(B85-C85) -> 0 | E85: =IF(D85<=0.001,"PASS","FAIL") -> PASS
A86: Health: score Balanced | B86: =Scenarios!B10 -> 32.136989 | C86: =Python_Ref!J9 -> 32.136989 | D86: =ABS(B86-C86) -> 0 | E86: =IF(D86<=0.01,"PASS","FAIL") -> PASS
A87: Health: rank Balanced | B87: =Scenarios!G10 -> 8 | C87: =Python_Ref!O9 -> 8 | D87: =ABS(B87-C87) -> 0 | E87: =IF(D87<=0,"PASS","FAIL") -> PASS
A88: Health: score Growth-led | B88: =Scenarios!C10 -> 33.455106 | C88: =Python_Ref!K9 -> 33.455106 | D88: =ABS(B88-C88) -> 0 | E88: =IF(D88<=0.01,"PASS","FAIL") -> PASS
A89: Health: rank Growth-led | B89: =Scenarios!H10 -> 8 | C89: =Python_Ref!P9 -> 8 | D89: =ABS(B89-C89) -> 0 | E89: =IF(D89<=0,"PASS","FAIL") -> PASS
A90: Health: score Risk-aware | B90: =Scenarios!D10 -> 35.148024 | C90: =Python_Ref!L9 -> 35.148024 | D90: =ABS(B90-C90) -> 0 | E90: =IF(D90<=0.01,"PASS","FAIL") -> PASS
A91: Health: rank Risk-aware | B91: =Scenarios!I10 -> 6 | C91: =Python_Ref!Q9 -> 6 | D91: =ABS(B91-C91) -> 0 | E91: =IF(D91<=0,"PASS","FAIL") -> PASS
A92: Health: score Scale-led | B92: =Scenarios!E10 -> 22.648024 | C92: =Python_Ref!M9 -> 22.648024 | D92: =ABS(B92-C92) -> 0 | E92: =IF(D92<=0.01,"PASS","FAIL") -> PASS
A93: Health: rank Scale-led | B93: =Scenarios!J10 -> 10 | C93: =Python_Ref!R9 -> 10 | D93: =ABS(B93-C93) -> 0 | E93: =IF(D93<=0,"PASS","FAIL") -> PASS
A94: Health: score Equal | B94: =Scenarios!F10 -> 32.636235 | C94: =Python_Ref!N9 -> 32.636235 | D94: =ABS(B94-C94) -> 0 | E94: =IF(D94<=0.01,"PASS","FAIL") -> PASS
A95: Health: rank Equal | B95: =Scenarios!K10 -> 8 | C95: =Python_Ref!S9 -> 8 | D95: =ABS(B95-C95) -> 0 | E95: =IF(D95<=0,"PASS","FAIL") -> PASS
A96: Consumer & Retail: value added | B96: =Scorecard!B12 -> 1105605 | C96: =Python_Ref!B10 -> 1105605 | D96: =ABS(B96-C96) -> 0 | E96: =IF(D96<=0.5,"PASS","FAIL") -> PASS
A97: Consumer & Retail: growth 2025 | B97: =Scorecard!D12 -> 5.5367401 | C97: =Python_Ref!D10 -> 5.5367401 | D97: =ABS(B97-C97) -> 0 | E97: =IF(D97<=0.001,"PASS","FAIL") -> PASS
A98: Consumer & Retail: CAGR | B98: =Scorecard!E12 -> 6.2588958 | C98: =Python_Ref!E10 -> 6.2588958 | D98: =ABS(B98-C98) -> 0 | E98: =IF(D98<=0.001,"PASS","FAIL") -> PASS
A99: Consumer & Retail: Q1 2026 growth | B99: =Scorecard!F12 -> 5.8041588 | C99: =Python_Ref!F10 -> 5.8041588 | D99: =ABS(B99-C99) -> 0 | E99: =IF(D99<=0.001,"PASS","FAIL") -> PASS
A100: Consumer & Retail: NPL ratio | B100: =Scorecard!H12 -> 20.191461 | C100: =Python_Ref!H10 -> 20.191461 | D100: =ABS(B100-C100) -> 0 | E100: =IF(D100<=0.001,"PASS","FAIL") -> PASS
...
